Workbook

Sheet 2025 RAC
A1: 日期 | B1: PI | C1: 型号 | D1: 数量 | E1: Contr # | F1: 客户Req date/需求ETD | G1: Actual ETD | H1: ETA | I1: 发票号 | J1: Destination | K1: Customer | L1: 清关资料 | M1: Remark
A2: 2024.10.31 | B2: PINMEL20241101022 | C2: MFAG26VA-N | D2: 25 | E2: RAC-025/ TGBU4948334 | G2: =VLOOKUP(CLEAN(SUBSTITUTE(TRIM(MID(E:E,FIND("/",E:E)+1,LEN(E:E)))," ","")),'Customs Decl. & Local Delivery'!D:I,6,0) -> 45656 | H2: =VLOOKUP(CLEAN(SUBSTITUTE(TRIM(MID(E:E,FIND("/",E:E)+1,LEN(E:E)))," ","")),'Customs Decl. & Local Delivery'!D:J,7,0) -> 45682 | I2: MDAJB241230D0005 | J2: VIC-Mel | K2: Polyaire | L2: Y | M2: polyaire PO #34610
A3: 2024.10.31 | B3: PINMEL20241101022 | C3: MFAG26VA-W | D3: 25 | G3: =G2 -> 45656 | H3: =H2 -> 45682 | I3: MDAJB241230D0005 | J3: VIC-Mel | K3: Polyaire | L3: Y | M3: REQ DATE:2024/ 1/23
A4: 2024.10.31 | B4: PINMEL20241101022 | C4: MFAG36VA-N | D4: 14 | G4: =G3 -> 45656 | H4: =H3 -> 45682 | I4: MDAJB241230D0005 | J4: VIC-Mel | K4: Polyaire | L4: Y
A5: 2024.10.31 | B5: PINMEL20241101022 | C5: MFAG36VA-W | D5: 14 | G5: =G4 -> 45656 | H5: =H4 -> 45682 | I5: MDAJB241230D0005 | J5: VIC-Mel | K5: Polyaire | L5: Y | M5: RAC CIF 928, POL-Beijiao, OOCL, LFD 21
A6: 2024.10.31 | B6: PINMEL20241101022 | C6: MFAG51VA-N | D6: 10 | G6: =G5 -> 45656 | H6: =H5 -> 45682 | I6: MDAJB241230D0005 | J6: VIC-Mel | K6: Polyaire | L6: Y
A7: 2024.10.31 | B7: PINMEL20241101022 | C7: MFAG51VA-W | D7: 10 | G7: =G6 -> 45656 | H7: =H6 -> 45682 | I7: MDAJB241230D0005 | J7: VIC-Mel | K7: Polyaire | L7: Y
A8: 2024.10.31 | B8: PINMEL20241101022 | C8: DUCMI105IHB | D8: 3 | G8: =G7 -> 45656 | H8: =H7 -> 45682 | I8: MDAJB241230D0005 | J8: VIC-Mel | K8: Polyaire | L8: Y
A9: 2024.10.31 | B9: PINMEL20241101022 | C9: UCMI105OB | D9: 3 | G9: =G8 -> 45656 | H9: =H8 -> 45682 | I9: MDAJB241230D0005 | J9: VIC-Mel | K9: Polyaire | L9: Y
A10: 2024.10.31 | B10: PINMEL20241101022 | C10: DUCMI125IHB | D10: 7 | G10: =G9 -> 45656 | H10: =H9 -> 45682 | I10: MDAJB241230D0005 | J10: VIC-Mel | K10: Polyaire | L10: Y
A11: 2024.10.31 | B11: PINMEL20241101022 | C11: UCMI125OB | D11: 7 | G11: =G10 -> 45656 | H11: =H10 -> 45682 | I11: MDAJB241230D0005 | J11: VIC-Mel | K11: Polyaire | L11: Y
A12: 2024.10.31 | B12: PINMEL20241101022 | C12: DUCMI140IHB | D12: 27 | G12: =G11 -> 45656 | H12: =H11 -> 45682 | I12: MDAJB241230D0005 | J12: VIC-Mel | K12: Polyaire | L12: Y
A13: 2024.10.31 | B13: PINMEL20241101022 | C13: UCMI140OB | D13: 27 | G13: =G12 -> 45656 | H13: =H12 -> 45682 | I13: MDAJB241230D0005 | J13: VIC-Mel | K13: Polyaire | L13: Y
A14: 2024.10.31 | B14: PINBRI20241101024 | C14: MFAB-26NC | D14: 50 | E14: RAC-001/ FSCU7105661 | G14: =VLOOKUP(CLEAN(SUBSTITUTE(TRIM(MID(E:E,FIND("/",E:E)+1,LEN(E:E)))," ","")),'Customs Decl. & Local Delivery'!D:I,6,0) -> 45660 | H14: =VLOOKUP(CLEAN(SUBSTITUTE(TRIM(MID(E:E,FIND("/",E:E)+1,LEN(E:E)))," ","")),'Customs Decl. & Local Delivery'!D:J,7,0) -> 45696 | I14: MDAJB250102D0049 | J14: QLD-Brisbane | K14: Polyaire | L14: Y | M14: polyaire PO #34622
A15: 2024.10.31 | B15: PINBRI20241101024 | C15: MFAB-26WC | D15: 50 | G15: =G14 -> 45660 | H15: =H14 -> 45696 | I15: MDAJB250102D0049 | J15: QLD-Brisbane | K15: Polyaire | L15: Y | M15: REQ DATE:2025/1/23
A16: 2024.10.31 | B16: PINBRI20241101024 | C16: MFAB-35NC | D16: 20 | G16: =G15 -> 45660 | H16: =H15 -> 45696 | I16: MDAJB250102D0049 | J16: QLD-Brisbane | K16: Polyaire | L16: Y | M16: 12月6日开会推后到1月出货
A17: 2024.10.31 | B17: PINBRI20241101024 | C17: MFAB-35WC | D17: 20 | G17: =G16 -> 45660 | H17: =H16 -> 45696 | I17: MDAJB250102D0049 | J17: QLD-Brisbane | K17: Polyaire | L17: Y | M17: RAC CIF,POL-Beijiao, USD 2000
A18: 2024.10.31 | B18: PINBRI20241101024 | C18: MFAB-50NC | D18: 20 | G18: =G17 -> 45660 | H18: =H17 -> 45696 | I18: MDAJB250102D0049 | J18: QLD-Brisbane | K18: Polyaire | L18: Y
A19: 2024.10.31 | B19: PINBRI20241101024 | C19: MFAB-50WC | D19: 20 | G19: =G18 -> 45660 | H19: =H18 -> 45696 | I19: MDAJB250102D0049 | J19: QLD-Brisbane | K19: Polyaire | L19: Y
A20: 2024.10.31 | B20: PINBRI20241101024 | C20: MFAB-71NC | D20: 28 | G20: =G19 -> 45660 | H20: =H19 -> 45696 | I20: MDAJB250102D0049 | J20: QLD-Brisbane | K20: Polyaire | L20: Y
A21: 2024.10.31 | B21: PINBRI20241101024 | C21: MFAB-71WC | D21: 28 | G21: =G20 -> 45660 | H21: =H20 -> 45696 | I21: MDAJB250102D0049 | J21: QLD-Brisbane | K21: Polyaire | L21: Y
A22: 2024.10.31 | B22: PINBRI20241101024 | C22: DUCMI105IHB | D22: 12 | G22: =G21 -> 45660 | H22: =H21 -> 45696 | I22: MDAJB250102D0049 | J22: QLD-Brisbane | K22: Polyaire | L22: Y
A23: 2024.10.31 | B23: PINBRI20241101024 | C23: UCMI105OB | D23: 12 | G23: =G22 -> 45660 | H23: =H22 -> 45696 | I23: MDAJB250102D0049 | J23: QLD-Brisbane | K23: Polyaire | L23: Y
A24: 2024.10.31 | B24: PINBRI20241101024 | C24: DUCMI125IHB | D24: 6 | G24: =G23 -> 45660 | H24: =H23 -> 45696 | I24: MDAJB250102D0049 | J24: QLD-Brisbane | K24: Polyaire | L24: Y
A25: 2024.10.31 | B25: PINBRI20241101024 | C25: UCMI125OB | D25: 6 | G25: =G24 -> 45660 | H25: =H24 -> 45696 | I25: MDAJB250102D0049 | J25: QLD-Brisbane | K25: Polyaire | L25: Y
A26: 2024.10.31 | B26: PINBRI20241101025 | C26: MFAB-20NC | D26: 35 | E26: RAC-002/ SLPU5000261 | G26: =VLOOKUP(CLEAN(SUBSTITUTE(TRIM(MID(E:E,FIND("/",E:E)+1,LEN(E:E)))," ","")),'Customs Decl. & Local Delivery'!D:I,6,0) -> 45660 | H26: =VLOOKUP(CLEAN(SUBSTITUTE(TRIM(MID(E:E,FIND("/",E:E)+1,LEN(E:E)))," ","")),'Customs Decl. & Local Delivery'!D:J,7,0) -> 45696 | I26: MDAJB250102D0048 | J26: QLD-Brisbane | K26: Polyaire | L26: Y | M26: polyaire PO #34624
A27: 2024.10.31 | B27: PINBRI20241101025 | C27: MFAB-20WC | D27: 35 | G27: =G26 -> 45660 | H27: =H26 -> 45696 | I27: MDAJB250102D0048 | J27: QLD-Brisbane | K27: Polyaire | L27: Y | M27: REQ DATE:2025/1/23
A28: 2024.10.31 | B28: PINBRI20241101025 | C28: MFAB-35NC | D28: 60 | G28: =G27 -> 45660 | H28: =H27 -> 45696 | I28: MDAJB250102D0048 | J28: QLD-Brisbane | K28: Polyaire | L28: Y | M28: 12月6日开会推后到1月出货
A29: 2024.10.31 | B29: PINBRI20241101025 | C29: MFAB-35WC | D29: 60 | G29: =G28 -> 45660 | H29: =H28 -> 45696 | I29: MDAJB250102D0048 | J29: QLD-Brisbane | K29: Polyaire | L29: Y | M29: RAC CIF,POL-Beijiao, USD 2000
A30: 2024.10.31 | B30: PINBRI20241101025 | C30: MFAB-50NC | D30: 15 | G30: =G29 -> 45660 | H30: =H29 -> 45696 | I30: MDAJB250102D0048 | J30: QLD-Brisbane | K30: Polyaire | L30: Y
A31: 2024.10.31 | B31: PINBRI20241101025 | C31: MFAB-50WC | D31: 15 | G31: =G30 -> 45660 | H31: =H30 -> 45696 | I31: MDAJB250102D0048 | J31: QLD-Brisbane | K31: Polyaire | L31: Y
A32: 2024.10.31 | B32: PINBRI20241101025 | C32: MFAB-71NC | D32: 30 | G32: =G31 -> 45660 | H32: =H31 -> 45696 | I32: MDAJB250102D0048 | J32: QLD-Brisbane | K32: Polyaire | L32: Y
A33: 2024.10.31 | B33: PINBRI20241101025 | C33: MFAB-71WC | D33: 30 | G33: =G32 -> 45660 | H33: =H32 -> 45696 | I33: MDAJB250102D0048 | J33: QLD-Brisbane | K33: Polyaire | L33: Y
A34: 2024.10.31 | B34: PINBRI20241101025 | C34: MFAB-81NC | D34: 5 | G34: =G33 -> 45660 | H34: =H33 -> 45696 | I34: MDAJB250102D0048 | J34: QLD-Brisbane | K34: Polyaire | L34: Y
A35: 2024.10.31 | B35: PINBRI20241101025 | C35: MFAB-81WC | D35: 5 | G35: =G34 -> 45660 | H35: =H34 -> 45696 | I35: MDAJB250102D0048 | J35: QLD-Brisbane | K35: Polyaire | L35: Y
A36: 2024.10.31 | B36: PINBRI20241101025 | C36: DUCMI105IHB | D36: 4 | G36: =G35 -> 45660 | H36: =H35 -> 45696 | I36: MDAJB250102D0048 | J36: QLD-Brisbane | K36: Polyaire | L36: Y
A37: 2024.10.31 | B37: PINBRI20241101025 | C37: UCMI105OB | D37: 4 | G37: =G36 -> 45660 | H37: =H36 -> 45696 | I37: MDAJB250102D0048 | J37: QLD-Brisbane | K37: Polyaire | L37: Y
A38: 2024.10.31 | B38: PINBRI20241101025 | C38: DUCMI125IHB | D38: 5 | G38: =G37 -> 45660 | H38: =H37 -> 45696 | I38: MDAJB250102D0048 | J38: QLD-Brisbane | K38: Polyaire | L38: Y
A39: 2024.10.31 | B39: PINBRI20241101025 | C39: UCMI125OB | D39: 5 | G39: =G38 -> 45660 | H39: =H38 -> 45696 | I39: MDAJB250102D0048 | J39: QLD-Brisbane | K39: Polyaire | L39: Y
A40: 2024.10.31 | B40: PINBRI20241101025 | C40: DUCMI170IHB | D40: 1 | G40: =G39 -> 45660 | H40: =H39 -> 45696 | I40: MDAJB250102D0048 | J40: QLD-Brisbane | K40: Polyaire | L40: Y
A41: 2024.10.31 | B41: PINBRI20241101025 | C41: UCMI170OB | D41: 1 | G41: =G40 -> 45660 | H41: =H40 -> 45696 | I41: MDAJB250102D0048 | J41: QLD-Brisbane | K41: Polyaire | L41: Y
A42: 2024.10.31 | B42: PINMEL20241101021 | C42: MFAG51VA-N | D42: 31 | E42: RAC-020/ GAOU7076396 | G42: =VLOOKUP(CLEAN(SUBSTITUTE(TRIM(MID(E:E,FIND("/",E:E)+1,LEN(E:E)))," ","")),'Customs Decl. & Local Delivery'!D:I,6,0) -> 45666 | H42: =VLOOKUP(CLEAN(SUBSTITUTE(TRIM(MID(E:E,FIND("/",E:E)+1,LEN(E:E)))," ","")),'Customs Decl. & Local Delivery'!D:J,7,0) -> 45685 | I42: MDAJB250101D0036 | J42: VIC-Mel | K42: Chromagen | L42: Y | M42: PO 540479
A43: 2024.10.31 | B43: PINMEL20241101021 | C43: MFAG51VA-W | D43: 31 | G43: =G42 -> 45666 | H43: =H42 -> 45685 | I43: MDAJB250101D0036 | J43: VIC-Mel | K43: Chromagen | L43: Y | M43: REQ DATE:2025/1/15
A44: 2024.10.31 | B44: PINMEL20241101021 | C44: MFAG70VA-N | D44: 78 | G44: =G43 -> 45666 | H44: =H43 -> 45685 | I44: MDAJB250101D0036 | J44: VIC-Mel | K44: Chromagen | L44: Y | M44: 已通知susu联系客户货代, 提前做booking
A45: 2024.10.31 | B45: PINMEL20241101021 | C45: MFAG70VA-W | D45: 78 | G45: =G44 -> 45666 | H45: =H44 -> 45685 | I45: MDAJB250101D0036 | J45: VIC-Mel | K45: Chromagen | L45: Y
A46: 2024.10.31 | B46: PINMEL20241101021 | C46: MFAG80VA-N | D46: 20 | G46: =G45 -> 45666 | H46: =H45 -> 45685 | I46: MDAJB250101D0036 | J46: VIC-Mel | K46: Chromagen | L46: Y
A47: 2024.10.31 | B47: PINMEL20241101021 | C47: MFAG80VA-W | D47: 20 | G47: =G46 -> 45666 | H47: =H46 -> 45685 | I47: MDAJB250101D0036 | J47: VIC-Mel | K47: Chromagen | L47: Y
A48: 2024.10.8 | B48: PINMEL202401015001 | C48: MFAG36VA-N | D48: 96 | E48: RAC-021/ TIIU5317991 | G48: =VLOOKUP(CLEAN(SUBSTITUTE(TRIM(MID(E:E,FIND("/",E:E)+1,LEN(E:E)))," ","")),'Customs Decl. & Local Delivery'!D:I,6,0) -> 45666 | H48: =VLOOKUP(CLEAN(SUBSTITUTE(TRIM(MID(E:E,FIND("/",E:E)+1,LEN(E:E)))," ","")),'Customs Decl. & Local Delivery'!D:J,7,0) -> 45685 | I48: MDAJB250101D0035 | J48: VIC-Mel | K48: Chromagen | L48: Y | M48: PO 538266
A49: 2024.10.8 | B49: PINMEL202401015001 | C49: MFAG51VA-N | D49: 48 | G49: =G48 -> 45666 | H49: =H48 -> 45685 | I49: MDAJB250101D0035 | J49: VIC-Mel | K49: Chromagen | L49: Y | M49: REQ DATE:2025/1/15
A50: 2024.10.8 | B50: PINMEL202401015001 | C50: MFAG70VA-N | D50: 48 | G50: =G49 -> 45666 | H50: =H49 -> 45685 | I50: MDAJB250101D0035 | J50: VIC-Mel | K50: Chromagen | L50: Y | M50: 已通知susu联系客户货代, 提前做booking
A51: 2024.10.8 | B51: PINMEL202401015001 | C51: MULMI0618B | D51: 48 | G51: =G50 -> 45666 | H51: =H50 -> 45685 | I51: MDAJB250101D0035 | J51: VIC-Mel | K51: Chromagen | L51: Y
A52: 2024.11.1 | B52: PINMEL20241101039 | C52: MFAG36VA-N | D52: 96 | E52: RAC-022/ GAOU7075297 | G52: =VLOOKUP(CLEAN(SUBSTITUTE(TRIM(MID(E:E,FIND("/",E:E)+1,LEN(E:E)))," ","")),'Customs Decl. & Local Delivery'!D:I,6,0) -> 45666 | H52: =VLOOKUP(CLEAN(SUBSTITUTE(TRIM(MID(E:E,FIND("/",E:E)+1,LEN(E:E)))," ","")),'Customs Decl. & Local Delivery'!D:J,7,0) -> 45685 | I52: MDAJB250101D0033 | J52: VIC-Mel | K52: Chromagen | L52: Y | M52: PO 541635
A53: 2024.11.1 | B53: PINMEL20241101039 | C53: MFAG51VA-N | D53: 48 | G53: =G52 -> 45666 | H53: =H52 -> 45685 | I53: MDAJB250101D0033 | J53: VIC-Mel | K53: Chromagen | L53: Y | M53: REQ DATE:2025/1/22
A54: 2024.11.1 | B54: PINMEL20241101039 | C54: MFAG70VA-N | D54: 48 | G54: =G53 -> 45666 | H54: =H53 -> 45685 | I54: MDAJB250101D0033 | J54: VIC-Mel | K54: Chromagen | L54: Y
A55: 2024.11.1 | B55: PINMEL20241101039 | C55: MULMI0618B | D55: 48 | E55: RAC-023/ TSSU5205250 | G55: =VLOOKUP(CLEAN(SUBSTITUTE(TRIM(MID(E:E,FIND("/",E:E)+1,LEN(E:E)))," ","")),'Customs Decl. & Local Delivery'!D:I,6,0) -> 45666 | H55: =VLOOKUP(CLEAN(SUBSTITUTE(TRIM(MID(E:E,FIND("/",E:E)+1,LEN(E:E)))," ","")),'Customs Decl. & Local Delivery'!D:J,7,0) -> 45685 | I55: MDAJB250101D0032 | J55: VIC-Mel | K55: Chromagen | L55: Y
A56: 2024.11.1 | B56: PINMEL20241101040 | C56: MFAG36VA-N | D56: 400 | G56: =G55 -> 45666 | H56: =H55 -> 45685 | I56: MDAJB250101D0032 | J56: VIC-Mel | K56: Chromagen | L56: Y | M56: PO 541637
A57: 2024.11.1 | B57: PINMEL20241101040 | C57: MFAG51VA-N | D57: 62 | G57: =G56 -> 45666 | H57: =H56 -> 45685 | I57: MDAJB250101D0032 | J57: VIC-Mel | K57: Chromagen | L57: Y | M57: REQ DATE:2025/1/22
A58: 2024.11.1 | B58: PINMEL20241101040 | C58: MFAG70VA-N | D58: 62 | G58: =G57 -> 45666 | H58: =H57 -> 45685 | I58: MDAJB250101D0032 | J58: VIC-Mel | K58: Chromagen | L58: Y
A59: 2024.11.1 | B59: PINMEL20241101040 | C59: MFAG80VA-N | D59: 62 | E59: RAC-024/ TXGU7367887 | G59: =VLOOKUP(CLEAN(SUBSTITUTE(TRIM(MID(E:E,FIND("/",E:E)+1,LEN(E:E)))," ","")),'Customs Decl. & Local Delivery'!D:I,6,0) -> 45666 | H59: =VLOOKUP(CLEAN(SUBSTITUTE(TRIM(MID(E:E,FIND("/",E:E)+1,LEN(E:E)))," ","")),'Customs Decl. & Local Delivery'!D:J,7,0) -> 45685 | I59: PINMEL20241101040 | J59: VIC-Mel | K59: Chromagen | L59: Y
A60: 2024.10.8 | B60: PINMEL202401015002 | C60: MFAG36VA-N | D60: 132 | G60: =G59 -> 45666 | H60: =H59 -> 45685 | I60: PINMEL20241101040 | J60: VIC-Mel | K60: Chromagen | L60: Y | M60: PO 538404
A61: 2024.10.8 | B61: PINMEL202401015002 | C61: MFAG70VA-N | D61: 66 | G61: =G60 -> 45666 | H61: =H60 -> 45685 | I61: PINMEL20241101040 | J61: VIC-Mel | K61: Chromagen | L61: Y | M61: REQ DATE:2025/1/15
A62: 2024.10.8 | B62: PINMEL202401015002 | C62: MULMI0513B | D62: 66 | G62: =G61 -> 45666 | H62: =H61 -> 45685 | I62: PINMEL20241101040 | J62: VIC-Mel | K62: Chromagen | L62: Y
A63: 2024.11.21 | B63: PINMEL20241121001 | C63: MFAG36VA-N | D63: 66 | E63: RAC-030/ BSIU9985610 | G63: =VLOOKUP(CLEAN(SUBSTITUTE(TRIM(MID(E:E,FIND("/",E:E)+1,LEN(E:E)))," ","")),'Customs Decl. & Local Delivery'!D:I,6,0) -> 45666 | H63: =VLOOKUP(CLEAN(SUBSTITUTE(TRIM(MID(E:E,FIND("/",E:E)+1,LEN(E:E)))," ","")),'Customs Decl. & Local Delivery'!D:J,7,0) -> 45698 | I63: MDAJB250107D0011 | J63: VIC-Mel | K63: Chromagen | L63: Y | M63: PO 544039
A64: 2024.11.21 | B64: PINMEL20241121001 | C64: MFAG51VA-N | D64: 44 | G64: =G63 -> 45666 | H64: =H63 -> 45698 | I64: MDAJB250107D0011 | J64: VIC-Mel | K64: Chromagen | L64: Y | M64: 客户要求ETD:1月第二周
A65: 2024.11.21 | B65: PINMEL20241121001 | C65: MFAG70VA-N | D65: 44 | G65: =G64 -> 45666 | H65: =H64 -> 45698 | I65: MDAJB250107D0011 | J65: VIC-Mel | K65: Chromagen | L65: Y
A66: 2024.11.21 | B66: PINMEL20241121001 | C66: MFAG80VA-N | D66: 44 | G66: =G65 -> 45666 | H66: =H65 -> 45698 | I66: MDAJB250107D0011 | J66: VIC-Mel | K66: Chromagen | L66: Y | M66: 已发susu出货安排提前做booking
A67: 2024.11.21 | B67: PINMEL20241121001 | C67: MULMI0513B | D67: 66 | G67: =G66 -> 45666 | H67: =H66 -> 45698 | I67: MDAJB250107D0011 | J67: VIC-Mel | K67: Chromagen | L67: Y
A68: 2024.10.8 | B68: PINMEL202401015003 | C68: MFAG36VA-N | D68: 96 | E68: RAC-031/ BMOU4748287 | G68: =VLOOKUP(CLEAN(SUBSTITUTE(TRIM(MID(E:E,FIND("/",E:E)+1,LEN(E:E)))," ","")),'Customs Decl. & Local Delivery'!D:I,6,0) -> 45666 | H68: =VLOOKUP(CLEAN(SUBSTITUTE(TRIM(MID(E:E,FIND("/",E:E)+1,LEN(E:E)))," ","")),'Customs Decl. & Local Delivery'!D:J,7,0) -> 45698 | I68: MDAJB250107D0011 | J68: VIC-Mel | K68: Chromagen | L68: Y | M68: PO 538267
A69: 2024.10.8 | B69: PINMEL202401015003 | C69: MFAG51VA-N | D69: 48 | G69: =G68 -> 45666 | H69: =H68 -> 45698 | I69: MDAJB250107D0011 | J69: VIC-Mel | K69: Chromagen | L69: Y | M69: REQ DATE:2025/2/15
A70: 2024.10.8 | B70: PINMEL202401015003 | C70: MFAG70VA-N | D70: 48 | G70: =G69 -> 45666 | H70: =H69 -> 45698 | I70: MDAJB250107D0011 | J70: VIC-Mel | K70: Chromagen | L70: Y | M70: 客户要求ETD:1月第二周
A71: 2024.10.8 | B71: PINMEL202401015003 | C71: MULMI0618B | D71: 48 | G71: =G70 -> 45666 | H71: =H70 -> 45698 | I71: MDAJB250107D0011 | J71: VIC-Mel | K71: Chromagen | L71: Y | M71: 已发susu出货安排提前做booking
A72: 2024.10.31 | B72: PINBRI20241101007 | C72: CASN-XG20 | D72: 25 | E72: RAC-003/ TSSU5099014 | G72: =VLOOKUP(CLEAN(SUBSTITUTE(TRIM(MID(E:E,FIND("/",E:E)+1,LEN(E:E)))," ","")),'Customs Decl. & Local Delivery'!D:I,6,0) -> 45667 | H72: =VLOOKUP(CLEAN(SUBSTITUTE(TRIM(MID(E:E,FIND("/",E:E)+1,LEN(E:E)))," ","")),'Customs Decl. & Local Delivery'!D:J,7,0) -> 45678 | I72: MDAJB241230D0012 | J72: QLD-Brisbane | K72: Fourways | L72: Y | M72: MARTIN SO 3930, FOB NANSHA,TSL
A73: 2024.10.31 | B73: PINBRI20241101007 | C73: CASG-XG20 | D73: 25 | G73: =G72 -> 45667 | H73: =H72 -> 45678 | I73: MDAJB241230D0012 | J73: QLD-Brisbane | K73: Fourways | L73: Y | M73: REQ DATE: 2025/1/2
A74: 2024.10.31 | B74: PINBRI20241101007 | C74: CASN-XG25 | D74: 65 | G74: =G73 -> 45667 | H74: =H73 -> 45678 | I74: MDAJB241230D0012 | J74: QLD-Brisbane | K74: Fourways | L74: Y
A75: 2024.10.31 | B75: PINBRI20241101007 | C75: CASG-XG25 | D75: 65 | G75: =G74 -> 45667 | H75: =H74 -> 45678 | I75: MDAJB241230D0012 | J75: QLD-Brisbane | K75: Fourways | L75: Y | M75: MARTIN SO 3930, FOB NANSHA,TSL（RAC 1月舱位补贴：CNY54300, for 29x40HQ）
A76: 2024.10.31 | B76: PINBRI20241101007 | C76: CASN-XG35 | D76: 25 | G76: =G75 -> 45667 | H76: =H75 -> 45678 | I76: MDAJB241230D0012 | J76: QLD-Brisbane | K76: Fourways | L76: Y
A77: 2024.10.31 | B77: PINBRI20241101007 | C77: CASG-XG35 | D77: 25 | G77: =G76 -> 45667 | H77: =H76 -> 45678 | I77: MDAJB241230D0012 | J77: QLD-Brisbane | K77: Fourways | L77: Y
A78: 2024.10.31 | B78: PINBRI20241101007 | C78: CASN-XG51 | D78: 30 | G78: =G77 -> 45667 | H78: =H77 -> 45678 | I78: MDAJB241230D0012 | J78: QLD-Brisbane | K78: Fourways | L78: Y
A79: 2024.10.31 | B79: PINBRI20241101007 | C79: CASG-XG51 | D79: 30 | G79: =G78 -> 45667 | H79: =H78 -> 45678 | I79: MDAJB241230D0012 | J79: QLD-Brisbane | K79: Fourways | L79: Y
A80: 2024.10.31 | B80: PINBRI20241101007 | C80: CASN-XG70 | D80: 30 | G80: =G79 -> 45667 | H80: =H79 -> 45678 | I80: MDAJB241230D0012 | J80: QLD-Brisbane | K80: Fourways | L80: Y
A81: 2024.10.31 | B81: PINBRI20241101007 | C81: CASG-XG70 | D81: 30 | G81: =G80 -> 45667 | H81: =H80 -> 45678 | I81: MDAJB241230D0012 | J81: QLD-Brisbane | K81: Fourways | L81: Y
A82: 2024.10.31 | B82: PINBRI20241101007 | C82: CASN-XG80 | D82: 10 | G82: =G81 -> 45667 | H82: =H81 -> 45678 | I82: MDAJB241230D0012 | J82: QLD-Brisbane | K82: Fourways | L82: Y
A83: 2024.10.31 | B83: PINBRI20241101007 | C83: CASG-XG80 | D83: 10 | G83: =G82 -> 45667 | H83: =H82 -> 45678 | I83: MDAJB241230D0012 | J83: QLD-Brisbane | K83: Fourways | L83: Y
A84: 2024.10.31 | B84: PINBRI20241101001 | C84: CASN-XG20 | D84: 25 | E84: RAC-004/ SEKU6007747 | G84: =VLOOKUP(CLEAN(SUBSTITUTE(TRIM(MID(E:E,FIND("/",E:E)+1,LEN(E:E)))," ","")),'Customs Decl. & Local Delivery'!D:I,6,0) -> 45667 | H84: =VLOOKUP(CLEAN(SUBSTITUTE(TRIM(MID(E:E,FIND("/",E:E)+1,LEN(E:E)))," ","")),'Customs Decl. & Local Delivery'!D:J,7,0) -> 45678 | I84: MDAJB250102D0019 | J84: QLD-Brisbane | K84: Fourways | L84: Y | M84: PO-00002331
A85: 2024.10.31 | B85: PINBRI20241101001 | C85: CASG-XG20 | D85: 25 | G85: =G84 -> 45667 | H85: =H84 -> 45678 | I85: MDAJB250102D0019 | J85: QLD-Brisbane | K85: Fourways | L85: Y | M85: REQ DATE: 2024.12/2
A86: 2024.10.31 | B86: PINBRI20241101001 | C86: CASN-XG25 | D86: 65 | G86: =G85 -> 45667 | H86: =H85 -> 45678 | I86: MDAJB250102D0019 | J86: QLD-Brisbane | K86: Fourways | L86: Y
A87: 2024.10.31 | B87: PINBRI20241101001 | C87: CASG-XG25 | D87: 65 | G87: =G86 -> 45667 | H87: =H86 -> 45678 | I87: MDAJB250102D0019 | J87: QLD-Brisbane | K87: Fourways | L87: Y | M87: MARTIN SO 3930, FOB NANSHA,TSL（RAC 1月舱位补贴：CNY54300, for 29x40HQ）
A88: 2024.10.31 | B88: PINBRI20241101001 | C88: CASN-XG35 | D88: 25 | G88: =G87 -> 45667 | H88: =H87 -> 45678 | I88: MDAJB250102D0019 | J88: QLD-Brisbane | K88: Fourways | L88: Y
A89: 2024.10.31 | B89: PINBRI20241101001 | C89: CASG-XG35 | D89: 25 | G89: =G88 -> 45667 | H89: =H88 -> 45678 | I89: MDAJB250102D0019 | J89: QLD-Brisbane | K89: Fourways | L89: Y
A90: 2024.10.31 | B90: PINBRI20241101001 | C90: CASN-XG51 | D90: 30 | G90: =G89 -> 45667 | H90: =H89 -> 45678 | I90: MDAJB250102D0019 | J90: QLD-Brisbane | K90: Fourways | L90: Y
A91: 2024.10.31 | B91: PINBRI20241101001 | C91: CASG-XG51 | D91: 30 | G91: =G90 -> 45667 | H91: =H90 -> 45678 | I91: MDAJB250102D0019 | J91: QLD-Brisbane | K91: Fourways | L91: Y
A92: 2024.10.31 | B92: PINBRI20241101001 | C92: CASN-XG70 | D92: 30 | G92: =G91 -> 45667 | H92: =H91 -> 45678 | I92: MDAJB250102D0019 | J92: QLD-Brisbane | K92: Fourways | L92: Y
A93: 2024.10.31 | B93: PINBRI20241101001 | C93: CASG-XG70 | D93: 30 | G93: =G92 -> 45667 | H93: =H92 -> 45678 | I93: MDAJB250102D0019 | J93: QLD-Brisbane | K93: Fourways | L93: Y
A94: 2024.10.31 | B94: PINBRI20241101001 | C94: CASN-XG80 | D94: 10 | G94: =G93 -> 45667 | H94: =H93 -> 45678 | I94: MDAJB250102D0019 | J94: QLD-Brisbane | K94: Fourways | L94: Y
A95: 2024.10.31 | B95: PINBRI20241101001 | C95: CASG-XG80 | D95: 10 | G95: =G94 -> 45667 | H95: =H94 -> 45678 | I95: MDAJB250102D0019 | J95: QLD-Brisbane | K95: Fourways | L95: Y
A96: 2024.12.4 | B96: PINBRI20241204001 | C96: MFAG20VA-N | D96: 15 | E96: RAC-005/ TLLU8855821 | G96: =VLOOKUP(CLEAN(SUBSTITUTE(TRIM(MID(E:E,FIND("/",E:E)+1,LEN(E:E)))," ","")),'Customs Decl. & Local Delivery'!D:I,6,0) -> 45667 | H96: =VLOOKUP(CLEAN(SUBSTITUTE(TRIM(MID(E:E,FIND("/",E:E)+1,LEN(E:E)))," ","")),'Customs Decl. & Local Delivery'!D:J,7,0) -> 45678 | I96: MDAJB250102D0008 | J96: QLD-Brisbane | K96: Polyaire | L96: Y | M96: polyaire PO #37264
A97: 2024.12.4 | B97: PINBRI20241204001 | C97: MFAG20VA-W | D97: 15 | G97: =G96 -> 45667 | H97: =H96 -> 45678 | I97: MDAJB250102D0008 | J97: QLD-Brisbane | K97: Polyaire | L97: Y | M97: REQ DATE: 2025/2/4
A98: 2024.12.4 | B98: PINBRI20241204001 | C98: MFAG26VA-N | D98: 85 | G98: =G97 -> 45667 | H98: =H97 -> 45678 | I98: MDAJB250102D0008 | J98: QLD-Brisbane | K98: Polyaire | L98: Y
A99: 2024.12.4 | B99: PINBRI20241204001 | C99: MFAG26VA-W | D99: 85 | G99: =G98 -> 45667 | H99: =H98 -> 45678 | I99: MDAJB250102D0008 | J99: QLD-Brisbane | K99: Polyaire | L99: Y | M99: MARTIN SO 3930, FOB NANSHA,TSL（RAC 1月舱位补贴：CNY54300, for 29x40HQ）
A100: 2024.12.4 | B100: PINBRI20241204001 | C100: MFAG36VA-N | D100: 20 | G100: =G99 -> 45667 | H100: =H99 -> 45678 | I100: MDAJB250102D0008 | J100: QLD-Brisbane | K100: Polyaire | L100: Y
...

Sheet 2025 MBT
A1: 日期 | B1: PI | C1: 型号 | D1: 数量 | E1: Contr # | F1: 客户Req date/需求ETD | G1: ETD | H1: ETA | I1: 发票号 | J1: Destination | K1: Customer | L1: 清关资料 | M1: Remark
A2: 2024.11.27 | B2: PI-MDA-20241127 | C2: MDV-V200WN1 (AU) | D2: 54 | E2: MBT-011/ BHCU4975791 | G2: =VLOOKUP(CLEAN(SUBSTITUTE(TRIM(MID(E:E,FIND("/",E:E)+1,LEN(E:E)))," ","")),'Customs Decl. & Local Delivery'!D:I,6,0) -> 45660 | H2: =VLOOKUP(CLEAN(SUBSTITUTE(TRIM(MID(E:E,FIND("/",E:E)+1,LEN(E:E)))," ","")),'Customs Decl. & Local Delivery'!D:J,7,0) -> 45687 | I2: MDCAS2501030020 | J2: VIC-Mel | K2: No | L2: Y | M2: MBT CIF CNY 18500，POL-BEIJIAO
A3: 2024.11.27 | B3: PI-MDA-20241127 | C3: MIH36GHN18 | D3: 72 | G3: =G2 -> 45660 | H3: =H2 -> 45687 | I3: MDCAS2501030020 | J3: VIC-Mel | K3: No | L3: Y | M3: RM23A遥控器+水泵+左右摆风+wifi内置
A4: 2024.11.27 | B4: PI-MDA-20241127 | C4: MIH45GHN18 | D4: 48 | G4: =G3 -> 45660 | H4: =H3 -> 45687 | I4: MDCAS2501030020 | J4: VIC-Mel | K4: No | L4: Y | M4: RM23A遥控器+水泵+左右摆风+wifi内置
A5: 2024.11.27 | B5: PI-MDA-20241127 | C5: MIH71GHN18 | D5: 60 | G5: =G4 -> 45660 | H5: =H4 -> 45687 | I5: MDCAS2501030020 | J5: VIC-Mel | K5: No | L5: Y | M5: RM23A遥控器+水泵+左右摆风+wifi内置
A6: 2024.11.27 | B6: PI-MDA-20241127 | C6: EEV线 | D6: 100 | G6: =G5 -> 45660 | H6: =H5 -> 45687 | I6: MDCAS2501030020 | J6: VIC-Mel | K6: No | L6: Y
A7: 2024.11.27 | B7: PI-MDA-20241127 | C7: MDV-V200WN1 (AU) | D7: 54 | E7: MBT-012/ BSIU9877805 | G7: =VLOOKUP(CLEAN(SUBSTITUTE(TRIM(MID(E:E,FIND("/",E:E)+1,LEN(E:E)))," ","")),'Customs Decl. & Local Delivery'!D:I,6,0) -> 45660 | H7: =VLOOKUP(CLEAN(SUBSTITUTE(TRIM(MID(E:E,FIND("/",E:E)+1,LEN(E:E)))," ","")),'Customs Decl. & Local Delivery'!D:J,7,0) -> 45687 | I7: MDCAS2501030020 | J7: VIC-Mel | K7: No | L7: Y | M7: MBT CIF CNY 18500，POL-BEIJIAO
A8: 2024.11.27 | B8: PI-MDA-20241127 | C8: MIH36GHN18 | D8: 12 | G8: =G7 -> 45660 | H8: =H7 -> 45687 | I8: MDCAS2501030020 | J8: VIC-Mel | K8: No | L8: Y | M8: RM23A遥控器+水泵+左右摆风+wifi内置
A9: 2024.11.27 | B9: PI-MDA-20241127 | C9: MIH45GHN18 | D9: 8 | G9: =G8 -> 45660 | H9: =H8 -> 45687 | I9: MDCAS2501030020 | J9: VIC-Mel | K9: No | L9: Y | M9: RM23A遥控器+水泵+左右摆风+wifi内置
A10: 2024.11.27 | B10: PI-MDA-20241127 | C10: MIH71GHN18 | D10: 10 | G10: =G9 -> 45660 | H10: =H9 -> 45687 | I10: MDCAS2501030020 | J10: VIC-Mel | K10: No | L10: Y | M10: RM23A遥控器+水泵+左右摆风+wifi内置
A11: 2024.11.27 | B11: PI-MDA-20241127 | C11: MIH36GHN18 | D11: 60 | G11: =G10 -> 45660 | H11: =H10 -> 45687 | I11: MDCAS2501030020 | J11: VIC-Mel | K11: No | L11: Y | M11: RM23A遥控器+水泵+左右摆风+wifi内置
A12: 2024.11.27 | B12: PI-MDA-20241127 | C12: MIH45GHN18 | D12: 40 | G12: =G11 -> 45660 | H12: =H11 -> 45687 | I12: MDCAS2501030020 | J12: VIC-Mel | K12: No | L12: Y | M12: RM23A遥控器+水泵+左右摆风+wifi内置
A13: 2024.11.27 | B13: PI-MDA-20241127 | C13: MIH71GHN18 | D13: 50 | G13: =G12 -> 45660 | H13: =H12 -> 45687 | I13: MDCAS2501030020 | J13: VIC-Mel | K13: No | L13: Y | M13: RM23A遥控器+水泵+左右摆风+wifi内置
A14: 2024.11.27 | B14: PI-MDA-20241127 | C14: RM23A遥控器 | D14: 100 | G14: =G13 -> 45660 | H14: =H13 -> 45687 | I14: MDCAS2501030020 | J14: VIC-Mel | K14: No | L14: Y
A15: 2024.11.27 | B15: PI-MDA-20241127 | C15: MDV-V200WN1 (AU) | D15: 54 | E15: MBT-013/ BSIU9886643 | G15: =VLOOKUP(CLEAN(SUBSTITUTE(TRIM(MID(E:E,FIND("/",E:E)+1,LEN(E:E)))," ","")),'Customs Decl. & Local Delivery'!D:I,6,0) -> 45660 | H15: =VLOOKUP(CLEAN(SUBSTITUTE(TRIM(MID(E:E,FIND("/",E:E)+1,LEN(E:E)))," ","")),'Customs Decl. & Local Delivery'!D:J,7,0) -> 45687 | I15: MDCAS2501030020 | J15: VIC-Mel | K15: No | L15: Y | M15: MBT CIF CNY 18500，POL-BEIJIAO
A16: 2024.11.27 | B16: PI-MDA-20241127 | C16: MIH36GHN18 | D16: 72 | G16: =G15 -> 45660 | H16: =H15 -> 45687 | I16: MDCAS2501030020 | J16: VIC-Mel | K16: No | L16: Y | M16: RM23A遥控器+水泵+左右摆风+wifi内置
A17: 2024.11.27 | B17: PI-MDA-20241127 | C17: MIH45GHN18 | D17: 48 | G17: =G16 -> 45660 | H17: =H16 -> 45687 | I17: MDCAS2501030020 | J17: VIC-Mel | K17: No | L17: Y | M17: RM23A遥控器+水泵+左右摆风+wifi内置
A18: 2024.11.27 | B18: PI-MDA-20241127 | C18: MIH71GHN18 | D18: 60 | G18: =G17 -> 45660 | H18: =H17 -> 45687 | I18: MDCAS2501030020 | J18: VIC-Mel | K18: No | L18: Y | M18: RM23A遥控器+水泵+左右摆风+wifi内置
A19: 2024.11.27 | B19: PI-MDA-20241127 | C19: MDV-V200WN1 (AU) | D19: 54 | E19: MBT-014/ FCIU7307262 | G19: =VLOOKUP(CLEAN(SUBSTITUTE(TRIM(MID(E:E,FIND("/",E:E)+1,LEN(E:E)))," ","")),'Customs Decl. & Local Delivery'!D:I,6,0) -> 45660 | H19: =VLOOKUP(CLEAN(SUBSTITUTE(TRIM(MID(E:E,FIND("/",E:E)+1,LEN(E:E)))," ","")),'Customs Decl. & Local Delivery'!D:J,7,0) -> 45687 | I19: MDCAS2501030020 | J19: VIC-Mel | K19: No | L19: Y | M19: MBT CIF CNY 18500，POL-BEIJIAO
A20: 2024.11.27 | B20: PI-MDA-20241127 | C20: MIH36GHN18 | D20: 72 | G20: =G19 -> 45660 | H20: =H19 -> 45687 | I20: MDCAS2501030020 | J20: VIC-Mel | K20: No | L20: Y | M20: RM23A遥控器+水泵+左右摆风+wifi内置
A21: 2024.11.27 | B21: PI-MDA-20241127 | C21: MIH45GHN18 | D21: 48 | G21: =G20 -> 45660 | H21: =H20 -> 45687 | I21: MDCAS2501030020 | J21: VIC-Mel | K21: No | L21: Y | M21: RM23A遥控器+水泵+左右摆风+wifi内置
A22: 2024.11.27 | B22: PI-MDA-20241127 | C22: MIH71GHN18 | D22: 60 | G22: =G21 -> 45660 | H22: =H21 -> 45687 | I22: MDCAS2501030020 | J22: VIC-Mel | K22: No | L22: Y | M22: RM23A遥控器+水泵+左右摆风+wifi内置
A23: 2024.11.27 | B23: PI-MDA-20241127 | C23: MDV-V200WN1 (AU) | D23: 54 | E23: MBT-015/ FDCU0006143 | G23: =VLOOKUP(CLEAN(SUBSTITUTE(TRIM(MID(E:E,FIND("/",E:E)+1,LEN(E:E)))," ","")),'Customs Decl. & Local Delivery'!D:I,6,0) -> 45660 | H23: =VLOOKUP(CLEAN(SUBSTITUTE(TRIM(MID(E:E,FIND("/",E:E)+1,LEN(E:E)))," ","")),'Customs Decl. & Local Delivery'!D:J,7,0) -> 45687 | I23: MDCAS2501030020 | J23: VIC-Mel | K23: Odisee | L23: Y | M23: MBT CIF CNY 18500，POL-BEIJIAO
A24: 2024.11.27 | B24: PI-MDA-20241127 | C24: MIH36GHN18 | D24: 72 | G24: =G23 -> 45660 | H24: =H23 -> 45687 | I24: MDCAS2501030020 | J24: VIC-Mel | K24: Odisee | L24: Y | M24: RM23A遥控器+水泵+左右摆风+wifi内置
A25: 2024.11.27 | B25: PI-MDA-20241127 | C25: MIH45GHN18 | D25: 48 | G25: =G24 -> 45660 | H25: =H24 -> 45687 | I25: MDCAS2501030020 | J25: VIC-Mel | K25: Odisee | L25: Y | M25: RM23A遥控器+水泵+左右摆风+wifi内置
A26: 2024.11.27 | B26: PI-MDA-20241127 | C26: MIH71GHN18 | D26: 60 | G26: =G25 -> 45660 | H26: =H25 -> 45687 | I26: MDCAS2501030020 | J26: VIC-Mel | K26: Odisee | L26: Y | M26: RM23A遥控器+水泵+左右摆风+wifi内置
A27: 2024.11.27 | B27: PI-MDA-20241127 | C27: MDV-V200WN1 (AU) | D27: 54 | E27: MBT-006/ FFAU4399308 | G27: =VLOOKUP(CLEAN(SUBSTITUTE(TRIM(MID(E:E,FIND("/",E:E)+1,LEN(E:E)))," ","")),'Customs Decl. & Local Delivery'!D:I,6,0) -> 45667 | H27: =VLOOKUP(CLEAN(SUBSTITUTE(TRIM(MID(E:E,FIND("/",E:E)+1,LEN(E:E)))," ","")),'Customs Decl. & Local Delivery'!D:J,7,0) -> 45685 | I27: MDCAS2501010082 | J27: VIC-Mel | K27: Odisee | L27: Y | M27: MBT CIF CNY 18500，POL-BEIJIAO
A28: 2024.11.27 | B28: PI-MDA-20241127 | C28: MIH36GHN18 | D28: 45 | G28: =G27 -> 45667 | H28: =H27 -> 45685 | I28: MDCAS2501010082 | J28: VIC-Mel | K28: Odisee | L28: Y | M28: RM23A遥控器+水泵+左右摆风+wifi内置
A29: 2024.11.27 | B29: PI-MDA-20241127 | C29: MIH45GHN18 | D29: 30 | G29: =G28 -> 45667 | H29: =H28 -> 45685 | I29: MDCAS2501010082 | J29: VIC-Mel | K29: Odisee | L29: Y | M29: RM23A遥控器+水泵+左右摆风+wifi内置
A30: 2024.11.27 | B30: PI-MDA-20241127 | C30: MIH71GHN18 | D30: 38 | G30: =G29 -> 45667 | H30: =H29 -> 45685 | I30: MDCAS2501010082 | J30: VIC-Mel | K30: Odisee | L30: Y | M30: RM23A遥控器+水泵+左右摆风+wifi内置
A31: 2024.11.27 | B31: PI-MDA-20241127 | C31: MIH80GHN18 | D31: 53 | G31: =G30 -> 45667 | H31: =H30 -> 45685 | I31: MDCAS2501010082 | J31: VIC-Mel | K31: Odisee | L31: Y | M31: RM23A遥控器+水泵+左右摆风+wifi内置
A32: 2024.11.27 | B32: PI-MDA-20241127 | C32: MDV-V200WN1 (AU) | D32: 54 | E32: MBT-007/ SEKU5869860 | G32: =VLOOKUP(CLEAN(SUBSTITUTE(TRIM(MID(E:E,FIND("/",E:E)+1,LEN(E:E)))," ","")),'Customs Decl. & Local Delivery'!D:I,6,0) -> 45667 | H32: =VLOOKUP(CLEAN(SUBSTITUTE(TRIM(MID(E:E,FIND("/",E:E)+1,LEN(E:E)))," ","")),'Customs Decl. & Local Delivery'!D:J,7,0) -> 45685 | I32: MDCAS2501010082 | J32: VIC-Mel | K32: Odisee | L32: Y | M32: MBT CIF CNY 18500，POL-BEIJIAO
A33: 2024.11.27 | B33: PI-MDA-20241127 | C33: MIH36GHN18 | D33: 45 | G33: =G32 -> 45667 | H33: =H32 -> 45685 | I33: MDCAS2501010082 | J33: VIC-Mel | K33: Odisee | L33: Y | M33: RM23A遥控器+水泵+左右摆风+wifi内置
A34: 2024.11.27 | B34: PI-MDA-20241127 | C34: MIH45GHN18 | D34: 30 | G34: =G33 -> 45667 | H34: =H33 -> 45685 | I34: MDCAS2501010082 | J34: VIC-Mel | K34: Odisee | L34: Y | M34: RM23A遥控器+水泵+左右摆风+wifi内置
A35: 2024.11.27 | B35: PI-MDA-20241127 | C35: MIH71GHN18 | D35: 38 | G35: =G34 -> 45667 | H35: =H34 -> 45685 | I35: MDCAS2501010082 | J35: VIC-Mel | K35: Odisee | L35: Y | M35: RM23A遥控器+水泵+左右摆风+wifi内置
A36: 2024.11.27 | B36: PI-MDA-20241127 | C36: MIH80GHN18 | D36: 53 | G36: =G35 -> 45667 | H36: =H35 -> 45685 | I36: MDCAS2501010082 | J36: VIC-Mel | K36: Odisee | L36: Y | M36: RM23A遥控器+水泵+左右摆风+wifi内置
A37: 2024.11.27 | B37: PI-MDA-20241127 | C37: MDV-V200WN1 (AU) | D37: 54 | E37: MBT-008/ TLLU7977152 | G37: =VLOOKUP(CLEAN(SUBSTITUTE(TRIM(MID(E:E,FIND("/",E:E)+1,LEN(E:E)))," ","")),'Customs Decl. & Local Delivery'!D:I,6,0) -> 45667 | H37: =VLOOKUP(CLEAN(SUBSTITUTE(TRIM(MID(E:E,FIND("/",E:E)+1,LEN(E:E)))," ","")),'Customs Decl. & Local Delivery'!D:J,7,0) -> 45685 | I37: MDCAS2501010082 | J37: VIC-Mel | K37: No | L37: Y | M37: MBT CIF CNY 18500，POL-BEIJIAO
A38: 2024.11.27 | B38: PI-MDA-20241127 | C38: MIH36GHN18 | D38: 45 | G38: =G37 -> 45667 | H38: =H37 -> 45685 | I38: MDCAS2501010082 | J38: VIC-Mel | K38: No | L38: Y | M38: RM23A遥控器+水泵+左右摆风+wifi内置
A39: 2024.11.27 | B39: PI-MDA-20241127 | C39: MIH45GHN18 | D39: 30 | G39: =G38 -> 45667 | H39: =H38 -> 45685 | I39: MDCAS2501010082 | J39: VIC-Mel | K39: No | L39: Y | M39: RM23A遥控器+水泵+左右摆风+wifi内置
A40: 2024.11.27 | B40: PI-MDA-20241127 | C40: MIH71GHN18 | D40: 38 | G40: =G39 -> 45667 | H40: =H39 -> 45685 | I40: MDCAS2501010082 | J40: VIC-Mel | K40: No | L40: Y | M40: RM23A遥控器+水泵+左右摆风+wifi内置
A41: 2024.11.27 | B41: PI-MDA-20241127 | C41: MIH80GHN18 | D41: 53 | G41: =G40 -> 45667 | H41: =H40 -> 45685 | I41: MDCAS2501010082 | J41: VIC-Mel | K41: No | L41: Y | M41: RM23A遥控器+水泵+左右摆风+wifi内置
A42: 2024.11.27 | B42: PI-MDA-20241127 | C42: MDV-V200WN1 (AU) | D42: 54 | E42: MBT-009/ TRHU4075007 | G42: =VLOOKUP(CLEAN(SUBSTITUTE(TRIM(MID(E:E,FIND("/",E:E)+1,LEN(E:E)))," ","")),'Customs Decl. & Local Delivery'!D:I,6,0) -> 45667 | H42: =VLOOKUP(CLEAN(SUBSTITUTE(TRIM(MID(E:E,FIND("/",E:E)+1,LEN(E:E)))," ","")),'Customs Decl. & Local Delivery'!D:J,7,0) -> 45685 | I42: MDCAS2501010082 | J42: VIC-Mel | K42: No | L42: Y | M42: MBT CIF CNY 18500，POL-BEIJIAO
A43: 2024.11.27 | B43: PI-MDA-20241127 | C43: MIH36GHN18 | D43: 45 | G43: =G42 -> 45667 | H43: =H42 -> 45685 | I43: MDCAS2501010082 | J43: VIC-Mel | K43: No | L43: Y | M43: RM23A遥控器+水泵+左右摆风+wifi内置
A44: 2024.11.27 | B44: PI-MDA-20241127 | C44: MIH45GHN18 | D44: 30 | G44: =G43 -> 45667 | H44: =H43 -> 45685 | I44: MDCAS2501010082 | J44: VIC-Mel | K44: No | L44: Y | M44: RM23A遥控器+水泵+左右摆风+wifi内置
A45: 2024.11.27 | B45: PI-MDA-20241127 | C45: MIH71GHN18 | D45: 38 | G45: =G44 -> 45667 | H45: =H44 -> 45685 | I45: MDCAS2501010082 | J45: VIC-Mel | K45: No | L45: Y | M45: RM23A遥控器+水泵+左右摆风+wifi内置
A46: 2024.11.27 | B46: PI-MDA-20241127 | C46: MIH80GHN18 | D46: 53 | G46: =G45 -> 45667 | H46: =H45 -> 45685 | I46: MDCAS2501010082 | J46: VIC-Mel | K46: No | L46: Y | M46: RM23A遥控器+水泵+左右摆风+wifi内置
A47: 2024.11.27 | B47: PI-MDA-20241127 | C47: MDV-V200WN1 (AU) | D47: 54 | E47: MBT-010/ TRHU4076615 | G47: =VLOOKUP(CLEAN(SUBSTITUTE(TRIM(MID(E:E,FIND("/",E:E)+1,LEN(E:E)))," ","")),'Customs Decl. & Local Delivery'!D:I,6,0) -> 45667 | H47: =VLOOKUP(CLEAN(SUBSTITUTE(TRIM(MID(E:E,FIND("/",E:E)+1,LEN(E:E)))," ","")),'Customs Decl. & Local Delivery'!D:J,7,0) -> 45685 | I47: MDCAS2501010082 | J47: VIC-Mel | K47: No | L47: Y | M47: MBT CIF CNY 18500，POL-BEIJIAO
A48: 2024.11.27 | B48: PI-MDA-20241127 | C48: MIH36GHN18 | D48: 45 | G48: =G47 -> 45667 | H48: =H47 -> 45685 | I48: MDCAS2501010082 | J48: VIC-Mel | K48: No | L48: Y | M48: RM23A遥控器+水泵+左右摆风+wifi内置
A49: 2024.11.27 | B49: PI-MDA-20241127 | C49: MIH45GHN18 | D49: 30 | G49: =G48 -> 45667 | H49: =H48 -> 45685 | I49: MDCAS2501010082 | J49: VIC-Mel | K49: No | L49: Y | M49: RM23A遥控器+水泵+左右摆风+wifi内置
A50: 2024.11.27 | B50: PI-MDA-20241127 | C50: MIH71GHN18 | D50: 38 | G50: =G49 -> 45667 | H50: =H49 -> 45685 | I50: MDCAS2501010082 | J50: VIC-Mel | K50: No | L50: Y | M50: RM23A遥控器+水泵+左右摆风+wifi内置
A51: 2024.11.27 | B51: PI-MDA-20241127 | C51: MIH80GHN18 | D51: 53 | G51: =G50 -> 45667 | H51: =H50 -> 45685 | I51: MDCAS2501010082 | J51: VIC-Mel | K51: No | L51: Y | M51: RM23A遥控器+水泵+左右摆风+wifi内置
A52: 2024.12.9 | B52: PI-MDA-PO 20241209 | C52: MIH80GHN18 | D52: 297 | E52: MBT-061/ SEKU5875879 | G52: =VLOOKUP(CLEAN(SUBSTITUTE(TRIM(MID(E:E,FIND("/",E:E)+1,LEN(E:E)))," ","")),'Customs Decl. & Local Delivery'!D:I,6,0) -> 45685 | H52: =VLOOKUP(CLEAN(SUBSTITUTE(TRIM(MID(E:E,FIND("/",E:E)+1,LEN(E:E)))," ","")),'Customs Decl. & Local Delivery'!D:J,7,0) -> 45708 | I52: MDCAS2501140013 | J52: VIC-Mel | K52: No | L52: Y | M52: RM23A遥控器+水泵+左右摆风+wifi内置，MBT CIF CNY 18500，POL-BEIJIAO
A53: 2024.12.12 | B53: PI-MDA-PO 20241212 | C53: MIH80GHN18 | D53: 68 | G53: =G52 -> 45685 | H53: =H52 -> 45708 | I53: MDCAS2501140013 | J53: VIC-Mel | K53: No | L53: Y | M53: RM23A遥控器+水泵+左右摆风+wifi内置
A54: 2024.12.12 | B54: PI-MDA-PO 20241212 | C54: MIH80GHN18 | D54: 175 | E54: MBT-062/ TSSU5055736 | G54: =VLOOKUP(CLEAN(SUBSTITUTE(TRIM(MID(E:E,FIND("/",E:E)+1,LEN(E:E)))," ","")),'Customs Decl. & Local Delivery'!D:I,6,0) -> 45685 | H54: =VLOOKUP(CLEAN(SUBSTITUTE(TRIM(MID(E:E,FIND("/",E:E)+1,LEN(E:E)))," ","")),'Customs Decl. & Local Delivery'!D:J,7,0) -> 45708 | I54: MDCAS2501140013 | J54: VIC-Mel | K54: No | L54: Y | M54: RM23A遥控器+水泵+左右摆风+wifi内置，MBT CIF CNY 18500，POL-BEIJIAO
A55: 2024.12.12 | B55: PI-MDA-PO 20241212 | C55: MIH36GHN18 | D55: 270 | G55: =G54 -> 45685 | H55: =H54 -> 45708 | I55: MDCAS2501140013 | J55: VIC-Mel | K55: No | L55: Y | M55: RM23A遥控器+水泵+左右摆风+wifi内置
A56: 2024.12.12 | B56: PI-MDA-PO 20241212 | C56: MIH36GHN18 | D56: 565 | E56: MBT-063/ TSSU5014439 | G56: =VLOOKUP(CLEAN(SUBSTITUTE(TRIM(MID(E:E,FIND("/",E:E)+1,LEN(E:E)))," ","")),'Customs Decl. & Local Delivery'!D:I,6,0) -> 45685 | H56: =VLOOKUP(CLEAN(SUBSTITUTE(TRIM(MID(E:E,FIND("/",E:E)+1,LEN(E:E)))," ","")),'Customs Decl. & Local Delivery'!D:J,7,0) -> 45708 | I56: MDCAS2501140013 | J56: VIC-Mel | K56: No | L56: Y | M56: RM23A遥控器+水泵+左右摆风+wifi内置，MBT CIF CNY 18500，POL-BEIJIAO
A57: 2024.12.17 | B57: PI-MDA-PO 20241217 | C57: RM12F1 | D57: 150 | E57: RAC-040/ TLLU8575245 | G57: =VLOOKUP(CLEAN(SUBSTITUTE(TRIM(MID(E:E,FIND("/",E:E)+1,LEN(E:E)))," ","")),'Customs Decl. & Local Delivery'!D:I,6,0) -> 45685 | H57: =VLOOKUP(CLEAN(SUBSTITUTE(TRIM(MID(E:E,FIND("/",E:E)+1,LEN(E:E)))," ","")),'Customs Decl. & Local Delivery'!D:J,7,0) -> 45708 | I57: MDCAS2501100015P | J57: VIC-Mel | K57: No | L57: Y
A58: 2024.11.27 | B58: PI-MDA-20241127 | C58: MDV-V230WN1(AU) | D58: 28 | E58: MBT-001/ TGHU6579284 | G58: =VLOOKUP(CLEAN(SUBSTITUTE(TRIM(MID(E:E,FIND("/",E:E)+1,LEN(E:E)))," ","")),'Customs Decl. & Local Delivery'!D:I,6,0) -> 45694 | H58: =VLOOKUP(CLEAN(SUBSTITUTE(TRIM(MID(E:E,FIND("/",E:E)+1,LEN(E:E)))," ","")),'Customs Decl. & Local Delivery'!D:J,7,0) -> 45712 | I58: MDCAS2501270001 | J58: VIC-Mel | K58: Odisee | L58: Y | M58: MBT CIF CNY 18500，POL-BEIJIAO， Odisee PO 1169
A59: 2024.11.27 | B59: PI-MDA-20241127 | C59: MIH200T1HN18(S) | D59: 28 | G59: =G58 -> 45694 | H59: =H58 -> 45712 | I59: MDCAS2501270001 | J59: VIC-Mel | K59: Odisee | L59: Y | M59: 在内机盒子里加86T线控器，原36套/柜，装柜问题，导致28套/柜，短装部分走DDP
A60: 2024.11.27 | B60: PI-MDA-20241127 | C60: MDV-V230WN1(AU) | D60: 28 | E60: MBT-002/ ONEU1697690 | G60: =VLOOKUP(CLEAN(SUBSTITUTE(TRIM(MID(E:E,FIND("/",E:E)+1,LEN(E:E)))," ","")),'Customs Decl. & Local Delivery'!D:I,6,0) -> 45694 | H60: =VLOOKUP(CLEAN(SUBSTITUTE(TRIM(MID(E:E,FIND("/",E:E)+1,LEN(E:E)))," ","")),'Customs Decl. & Local Delivery'!D:J,7,0) -> 45712 | I60: MDCAS2501270001 | J60: VIC-Mel | K60: Odisee | L60: Y | M60: MBT CIF CNY 18500，POL-BEIJIAO， Odisee PO 1170
A61: 2024.11.27 | B61: PI-MDA-20241127 | C61: MIH200T1HN18(S) | D61: 28 | G61: =G60 -> 45694 | H61: =H60 -> 45712 | I61: MDCAS2501270001 | J61: VIC-Mel | K61: Odisee | L61: Y | M61: 在内机盒子里加86T线控器，原36套/柜，装柜问题，导致28套/柜，短装部分走DDP
A62: 2024.11.27 | B62: PI-MDA-20241127 | C62: MDV-V230WN1(AU) | D62: 28 | E62: MBT-003/ KKFU7869930 | G62: =VLOOKUP(CLEAN(SUBSTITUTE(TRIM(MID(E:E,FIND("/",E:E)+1,LEN(E:E)))," ","")),'Customs Decl. & Local Delivery'!D:I,6,0) -> 45694 | H62: =VLOOKUP(CLEAN(SUBSTITUTE(TRIM(MID(E:E,FIND("/",E:E)+1,LEN(E:E)))," ","")),'Customs Decl. & Local Delivery'!D:J,7,0) -> 45712 | I62: MDCAS2501270001 | J62: VIC-Mel | K62: Polyaire | L62: Y | M62: MBT CIF CNY 18500，POL-BEIJIAO，Polyaire PO 40414
A63: 2024.11.27 | B63: PI-MDA-20241127 | C63: MIH200T1HN18(S) | D63: 28 | G63: =G62 -> 45694 | H63: =H62 -> 45712 | I63: MDCAS2501270001 | J63: VIC-Mel | K63: Polyaire | L63: Y | M63: 在内机盒子里加86T线控器，原36套/柜，装柜问题，导致28套/柜，短装部分走DDP
A64: 2024.11.27 | B64: PI-MDA-20241127 | C64: MDV-V230WN1(AU) | D64: 28 | E64: MBT-004/ GCXU5227617 | G64: =VLOOKUP(CLEAN(SUBSTITUTE(TRIM(MID(E:E,FIND("/",E:E)+1,LEN(E:E)))," ","")),'Customs Decl. & Local Delivery'!D:I,6,0) -> 45694 | H64: =VLOOKUP(CLEAN(SUBSTITUTE(TRIM(MID(E:E,FIND("/",E:E)+1,LEN(E:E)))," ","")),'Customs Decl. & Local Delivery'!D:J,7,0) -> 45712 | I64: MDCAS2501270001 | J64: VIC-Mel | K64: Polyaire | L64: Y | M64: MBT CIF CNY 18500，POL-BEIJIAO，Polyaire PO 40415
A65: 2024.11.27 | B65: PI-MDA-20241127 | C65: MIH200T1HN18(S) | D65: 28 | G65: =G64 -> 45694 | H65: =H64 -> 45712 | I65: MDCAS2501270001 | J65: VIC-Mel | K65: Polyaire | L65: Y | M65: 在内机盒子里加86T线控器，原36套/柜，装柜问题，导致28套/柜，短装部分走DDP
A66: 2024.11.27 | B66: PI-MDA-20241127 | C66: MDV-V230WN1(AU) | D66: 18 | E66: MBT-021/ SNBU8363594 | G66: =VLOOKUP(CLEAN(SUBSTITUTE(TRIM(MID(E:E,FIND("/",E:E)+1,LEN(E:E)))," ","")),'Customs Decl. & Local Delivery'!D:I,6,0) -> 45692 | H66: =VLOOKUP(CLEAN(SUBSTITUTE(TRIM(MID(E:E,FIND("/",E:E)+1,LEN(E:E)))," ","")),'Customs Decl. & Local Delivery'!D:J,7,0) -> 45709 | I66: MDCAS2501260036 | J66: VIC-Mel | K66: No | L66: Y | M66: MBT CIF CNY 18500，POL-BEIJIAO
A67: 2024.11.27 | B67: PI-MDA-20241127 | C67: MIH200T1HN18(S) | D67: 18 | G67: =G66 -> 45692 | H67: =H66 -> 45709 | I67: MDCAS2501260036 | J67: VIC-Mel | K67: No | L67: Y | M67: 在内机盒子里加86T线控器
A68: 2024.11.27 | B68: PI-MDA-20241127 | C68: MIH36GHN18 | D68: 15 | G68: =G67 -> 45692 | H68: =H67 -> 45709 | I68: MDCAS2501260036 | J68: VIC-Mel | K68: No | L68: Y | M68: RM23A遥控器+水泵+左右摆风+wifi内置
A69: 2024.11.27 | B69: PI-MDA-20241127 | C69: MIH45GHN18 | D69: 10 | G69: =G68 -> 45692 | H69: =H68 -> 45709 | I69: MDCAS2501260036 | J69: VIC-Mel | K69: No | L69: Y | M69: RM23A遥控器+水泵+左右摆风+wifi内置
A70: 2024.11.27 | B70: PI-MDA-20241127 | C70: MIH71GHN18 | D70: 10 | G70: =G69 -> 45692 | H70: =H69 -> 45709 | I70: MDCAS2501260036 | J70: VIC-Mel | K70: No | L70: Y | M70: RM23A遥控器+水泵+左右摆风+wifi内置
A71: 2024.11.27 | B71: PI-MDA-20241127 | C71: MIH80GHN18 | D71: 85 | G71: =G70 -> 45692 | H71: =H70 -> 45709 | I71: MDCAS2501260036 | J71: VIC-Mel | K71: No | L71: Y | M71: RM23A遥控器+水泵+左右摆风+wifi内置
A72: 2024.12.2 | B72: PINMEL20241202001 | C72: MFAG80VA-N | D72: 15 | G72: =G71 -> 45692 | H72: =H71 -> 45709 | I72: MDAJB250127D0006 | J72: VIC-Mel | K72: No | L72: Y | M72: RAC的货
A73: 2024.11.27 | B73: PI-MDA-20241127 | C73: MDV-V235WN1(AU)-A | D73: 36 | E73: MBT-030/ SNBU8275317 | G73: =VLOOKUP(CLEAN(SUBSTITUTE(TRIM(MID(E:E,FIND("/",E:E)+1,LEN(E:E)))," ","")),'Customs Decl. & Local Delivery'!D:I,6,0) -> 45695 | H73: =VLOOKUP(CLEAN(SUBSTITUTE(TRIM(MID(E:E,FIND("/",E:E)+1,LEN(E:E)))," ","")),'Customs Decl. & Local Delivery'!D:J,7,0) -> 45717 | I73: MDCAS2502070003 | J73: VIC-Mel | K73: No | L73: Y | M73: MBT CIF CNY 18500，POL-BEIJIAO
A74: 2024.11.27 | B74: PI-MDA-20241127 | C74: MIH28GHN18-A | D74: 5 | G74: =G73 -> 45695 | H74: =H73 -> 45717 | I74: MDCAS2502070003 | J74: VIC-Mel | K74: No | L74: Y | M74: 内机包装含PQE+EEV线
A75: 2024.11.27 | B75: PI-MDA-20241127 | C75: MIH36GHN18-A | D75: 60 | G75: =G74 -> 45695 | H75: =H74 -> 45717 | I75: MDCAS2502070003 | J75: VIC-Mel | K75: No | L75: Y | M75: 内机包装含PQE+EEV线
A76: 2024.11.27 | B76: PI-MDA-20241127 | C76: MIH45GHN18-A | D76: 5 | G76: =G75 -> 45695 | H76: =H75 -> 45717 | I76: MDCAS2502070003 | J76: VIC-Mel | K76: No | L76: Y | M76: 内机包装含PQE+EEV线
A77: 2024.11.27 | B77: PI-MDA-20241127 | C77: MIH56GHN18-A | D77: 30 | G77: =G76 -> 45695 | H77: =H76 -> 45717 | I77: MDCAS2502070003 | J77: VIC-Mel | K77: No | L77: Y | M77: 内机包装含PQE+EEV线
A78: 2024.11.27 | B78: PI-MDA-20241127 | C78: MIH80GHN18-A | D78: 30 | G78: =G77 -> 45695 | H78: =H77 -> 45717 | I78: MDCAS2502070003 | J78: VIC-Mel | K78: No | L78: Y | M78: 内机包装含PQE+EEV线
A79: 2024.11.27 | B79: PI-MDA-20241127 | C79: MDV-V235WN1(AU)-A | D79: 36 | E79: MBT-031/ SNBU8303764 | G79: =VLOOKUP(CLEAN(SUBSTITUTE(TRIM(MID(E:E,FIND("/",E:E)+1,LEN(E:E)))," ","")),'Customs Decl. & Local Delivery'!D:I,6,0) -> 45695 | H79: =VLOOKUP(CLEAN(SUBSTITUTE(TRIM(MID(E:E,FIND("/",E:E)+1,LEN(E:E)))," ","")),'Customs Decl. & Local Delivery'!D:J,7,0) -> 45717 | I79: MDCAS2502070003 | J79: VIC-Mel | K79: No | L79: Y | M79: MBT CIF CNY 18500，POL-BEIJIAO
A80: 2024.11.27 | B80: PI-MDA-20241127 | C80: MIH28GHN18-A | D80: 5 | G80: =G79 -> 45695 | H80: =H79 -> 45717 | I80: MDCAS2502070003 | J80: VIC-Mel | K80: No | L80: Y | M80: 内机包装含PQE+EEV线
A81: 2024.11.27 | B81: PI-MDA-20241127 | C81: MIH36GHN18-A | D81: 60 | G81: =G80 -> 45695 | H81: =H80 -> 45717 | I81: MDCAS2502070003 | J81: VIC-Mel | K81: No | L81: Y | M81: 内机包装含PQE+EEV线
A82: 2024.11.27 | B82: PI-MDA-20241127 | C82: MIH45GHN18-A | D82: 5 | G82: =G81 -> 45695 | H82: =H81 -> 45717 | I82: MDCAS2502070003 | J82: VIC-Mel | K82: No | L82: Y | M82: 内机包装含PQE+EEV线
A83: 2024.11.27 | B83: PI-MDA-20241127 | C83: MIH56GHN18-A | D83: 30 | G83: =G82 -> 45695 | H83: =H82 -> 45717 | I83: MDCAS2502070003 | J83: VIC-Mel | K83: No | L83: Y | M83: 内机包装含PQE+EEV线
A84: 2024.11.27 | B84: PI-MDA-20241127 | C84: MIH80GHN18-A | D84: 30 | G84: =G83 -> 45695 | H84: =H83 -> 45717 | I84: MDCAS2502070003 | J84: VIC-Mel | K84: No | L84: Y | M84: 内机包装含PQE+EEV线
A85: 2024.11.27 | B85: PI-MDA-20241127 | C85: MDV-V235WN1(AU)-A | D85: 36 | E85: MBT-032/ SNBU8203385 | G85: =VLOOKUP(CLEAN(SUBSTITUTE(TRIM(MID(E:E,FIND("/",E:E)+1,LEN(E:E)))," ","")),'Customs Decl. & Local Delivery'!D:I,6,0) -> 45695 | H85: =VLOOKUP(CLEAN(SUBSTITUTE(TRIM(MID(E:E,FIND("/",E:E)+1,LEN(E:E)))," ","")),'Customs Decl. & Local Delivery'!D:J,7,0) -> 45717 | I85: MDCAS2502070003 | J85: VIC-Mel | K85: No | L85: Y | M85: MBT CIF CNY 18500，POL-BEIJIAO
A86: 2024.11.27 | B86: PI-MDA-20241127 | C86: MIH28GHN18-A | D86: 5 | G86: =G85 -> 45695 | H86: =H85 -> 45717 | I86: MDCAS2502070003 | J86: VIC-Mel | K86: No | L86: Y | M86: 内机包装含PQE+EEV线
A87: 2024.11.27 | B87: PI-MDA-20241127 | C87: MIH36GHN18-A | D87: 60 | G87: =G86 -> 45695 | H87: =H86 -> 45717 | I87: MDCAS2502070003 | J87: VIC-Mel | K87: No | L87: Y | M87: 内机包装含PQE+EEV线
A88: 2024.11.27 | B88: PI-MDA-20241127 | C88: MIH45GHN18-A | D88: 5 | G88: =G87 -> 45695 | H88: =H87 -> 45717 | I88: MDCAS2502070003 | J88: VIC-Mel | K88: No | L88: Y | M88: 内机包装含PQE+EEV线
A89: 2024.11.27 | B89: PI-MDA-20241127 | C89: MIH56GHN18-A | D89: 30 | G89: =G88 -> 45695 | H89: =H88 -> 45717 | I89: MDCAS2502070003 | J89: VIC-Mel | K89: No | L89: Y | M89: 内机包装含PQE+EEV线
A90: 2024.11.27 | B90: PI-MDA-20241127 | C90: MIH80GHN18-A | D90: 30 | G90: =G89 -> 45695 | H90: =H89 -> 45717 | I90: MDCAS2502070003 | J90: VIC-Mel | K90: No | L90: Y | M90: 内机包装含PQE+EEV线
A91: 2024.11.27 | B91: PI-MDA-20241127 | C91: MDV-V235WN1(AU)-A | D91: 36 | E91: MBT-033/ SNBU8266911 | G91: =VLOOKUP(CLEAN(SUBSTITUTE(TRIM(MID(E:E,FIND("/",E:E)+1,LEN(E:E)))," ","")),'Customs Decl. & Local Delivery'!D:I,6,0) -> 45695 | H91: =VLOOKUP(CLEAN(SUBSTITUTE(TRIM(MID(E:E,FIND("/",E:E)+1,LEN(E:E)))," ","")),'Customs Decl. & Local Delivery'!D:J,7,0) -> 45717 | I91: MDCAS2502070003 | J91: VIC-Mel | K91: No | L91: Y | M91: MBT CIF CNY 18500，POL-BEIJIAO
A92: 2024.11.27 | B92: PI-MDA-20241127 | C92: MIH28GHN18-A | D92: 5 | G92: =G91 -> 45695 | H92: =H91 -> 45717 | I92: MDCAS2502070003 | J92: VIC-Mel | K92: No | L92: Y | M92: 内机包装含PQE+EEV线
A93: 2024.11.27 | B93: PI-MDA-20241127 | C93: MIH36GHN18-A | D93: 60 | G93: =G92 -> 45695 | H93: =H92 -> 45717 | I93: MDCAS2502070003 | J93: VIC-Mel | K93: No | L93: Y | M93: 内机包装含PQE+EEV线
A94: 2024.11.27 | B94: PI-MDA-20241127 | C94: MIH45GHN18-A | D94: 5 | G94: =G93 -> 45695 | H94: =H93 -> 45717 | I94: MDCAS2502070003 | J94: VIC-Mel | K94: No | L94: Y | M94: 内机包装含PQE+EEV线
A95: 2024.11.27 | B95: PI-MDA-20241127 | C95: MIH56GHN18-A | D95: 30 | G95: =G94 -> 45695 | H95: =H94 -> 45717 | I95: MDCAS2502070003 | J95: VIC-Mel | K95: No | L95: Y | M95: 内机包装含PQE+EEV线
A96: 2024.11.27 | B96: PI-MDA-20241127 | C96: MIH80GHN18-A | D96: 30 | G96: =G95 -> 45695 | H96: =H95 -> 45717 | I96: MDCAS2502070003 | J96: VIC-Mel | K96: No | L96: Y | M96: 内机包装含PQE+EEV线
A97: 2024.11.27 | B97: PI-MDA-20241127 | C97: MDV-V235WN1(AU)-A | D97: 36 | E97: MBT-034/ SNBU8285450 | G97: =VLOOKUP(CLEAN(SUBSTITUTE(TRIM(MID(E:E,FIND("/",E:E)+1,LEN(E:E)))," ","")),'Customs Decl. & Local Delivery'!D:I,6,0) -> 45695 | H97: =VLOOKUP(CLEAN(SUBSTITUTE(TRIM(MID(E:E,FIND("/",E:E)+1,LEN(E:E)))," ","")),'Customs Decl. & Local Delivery'!D:J,7,0) -> 45717 | I97: MDCAS2502070003 | J97: VIC-Mel | K97: No | L97: Y | M97: MBT CIF CNY 18500，POL-BEIJIAO
A98: 2024.11.27 | B98: PI-MDA-20241127 | C98: MIH28GHN18-A | D98: 5 | G98: =G97 -> 45695 | H98: =H97 -> 45717 | I98: MDCAS2502070003 | J98: VIC-Mel | K98: No | L98: Y | M98: 内机包装含PQE+EEV线
A99: 2024.11.27 | B99: PI-MDA-20241127 | C99: MIH36GHN18-A | D99: 60 | G99: =G98 -> 45695 | H99: =H98 -> 45717 | I99: MDCAS2502070003 | J99: VIC-Mel | K99: No | L99: Y | M99: 内机包装含PQE+EEV线
A100: 2024.11.27 | B100: PI-MDA-20241127 | C100: MIH45GHN18-A | D100: 5 | G100: =G99 -> 45695 | H100: =H99 -> 45717 | I100: MDCAS2502070003 | J100: VIC-Mel | K100: No | L100: Y | M100: 内机包装含PQE+EEV线
...

Sheet Customs Decl. & Local Delivery
A1: PO Date | B1: Midea Department | C1: BL No | D1: Container # | E1: Sea freight cost | F1: Terms | G1: Shipping Company | H1: Vessel Voy # | I1: ETD | J1: ETA | K1: Destination | L1: Warehouse address | M1: PO# | N1: 清关 | O1: GST | P1: 卸柜费用(AUD) | Q1: CCL Docs | R1: tax invoice send | S1: tax payment | T1: EDO send | U1: Delivery Date | V1: 还柜Y/N | W1: LFD | X1: Remark
A2: 2023.9.12 | C2: ZIMUIAU3028180 | D2: ZCSU7532999 | G2: ZIM | H2: SUI SHUN FENG JI 968 231225 | I2: 45285 | J2: 45306 | K2: QLD-Brisbane | L2: Unit 2 60 Dulacca Street Acacia Ridge QLD 4110 | M2: Polyaire 12439 | Q2: 45299 | U2: 45313 | V2: Y | W2: =J2+14 -> 45320 | X2: 6sets of Training Rack Wrongly Loaded in by RAC
A3: 2023.11.20 | C3: 712310681045 | D3: TSSU5163181 | G3: TSL | H3: TS VANCOUVER/2306S | I3: 45290 | J3: 45307 | K3: NSW-Sydney | L3: Syd Warehouse | M3: - | Q3: 45297 | U3: 45313 | V3: Y | W3: =J3+14 -> 45321
A4: 2023.9.22 | C4: ZIMUIAU3028182 | D4: ZCSU6984356 | G4: ZIM | H4: SUI SHUN FENG JI 968 231225 | I4: 45285 | J4: 45310 | K4: Vic-Mel | L4: Mel Warehouse | M4: - | Q4: 45289 | U4: 45320 | V4: Y | W4: =J4+14 -> 45324
A5: 2023.11.20 | C5: ZIMUGZH0351951 | D5: ZCSU7632581 | G5: ZIM | H5: ZIM GANGES 1/S | I5: 45292 | J5: 45310 | K5: VIC-Mel | L5: Mel Warehouse | M5: - | Q5: 45297 | U5: 45320 | V5: Y | W5: =J5+14 -> 45324
A6: 2023.11.20 | C6: ZIMUGZH0351952 | D6: ZCSU6797458 | G6: ZIM | H6: ZIM GANGES 1/S | I6: 45292 | J6: 45310 | K6: VIC-Mel | L6: Mel Warehouse | M6: - | Q6: 45297 | U6: 45320 | V6: Y | W6: =J6+14 -> 45324
A7: 2023.10.10 | C7: ZIMUIAU3028181 | D7: ZCSU6604292 | G7: ZIM | H7: SHUN YI 818/231226 | I7: 45285 | J7: 45310 | K7: VIC-Mel | L7: Mel Warehouse | M7: - | Q7: 45299 | U7: 45320 | V7: Y | W7: =J7+14 -> 45324
A8: 2023.12.8 | C8: ZIMUGZH0353919 | D8: ZCSU7049105 | G8: ZIM | H8: ZIM GANGES 1/S | I8: 45297 | J8: 45310 | K8: VIC-Mel | L8: Mel Warehouse | M8: - | Q8: 45303 | U8: 45321 | V8: Y | W8: =J8+14 -> 45324
A9: 2023.11.20 | C9: ZIMUGZH0351956 | D9: ZCSU7232970 | G9: ZIM | H9: ZIM GANGES 1/S | I9: 45291 | J9: 45310 | K9: VIC-Mel | L9: Mel Warehouse | M9: - | Q9: 45303 | U9: 45320 | V9: Y | W9: =J9+14 -> 45324
A10: 2023.11.20 | C10: 712310678380 | D10: FFAU4387082 | G10: TSL | H10: TS VANCOUVER/2306S | I10: 45290 | J10: 45312 | K10: VIC-Mel | L10: Mel Warehouse | M10: - | Q10: 45296 | U10: 45316 | V10: Y | W10: =J10+14 -> 45326
A11: 2023.10.17 | C11: ZIMUIAU3028183 | D11: UETU5272451 | G11: ZIM | H11: GAO LAN 813/231226 | I11: 45285 | J11: 45320 | K11: NSW-Sydney | L11: 71/NSW - 71 Padstow 50 GIBSON AVENUE Padstow NSW 2211 changed to 6 Avalli Road, Prestons, NSW 2170 | M11: Polyaire 14578 | Q11: 45295 | U11: 45327 | V11: Y | W11: =J11+14 -> 45334 | X11: delayed ETA from 1/19 to 1/29
A12: 2023.10.20 | C12: COSU8045938370 | D12: OOLU6882120 | G12: COSCO | H12: JIN RONG 02 / 078S | I12: 45280 | J12: 45335 | K12: WA-Frementle | L12: 61 Conquest Way, Wangara WA 6065 | M12: Polyaire 14809 | Q12: 45289 | U12: 45337 | V12: Y | W12: =J12+17 -> 45352 | X12: 2pcs of UCMI105OB for aftersales units, Delivery rejected by Polyaire due to Maersk didn't deliver after approval provided
A13: 2024.2.3 | C13: SZCK30090100 | D13: PCIU8558072 | G13: PIL | H13: TS HOCHIMINH 2308S | I13: 45322 | J13: 45337 | K13: VIC-Mel | L13: Mel Warehouse | M13: - | Q13: 45325 | U13: 45343 | V13: Y | W13: =J13+14 -> 45351
A14: 2023.12.8 | C14: OOLU2731653561 | D14: OOCU7951147 | G14: OOCL | H14: CMA CGM MONTMARTRE 0FMEXW1MA | I14: 45329 | J14: 45353 | K14: WA-Frementle | L14: 61 Conquest Way, Wangara WA 6065 | M14: Polyaire 17927 | Q14: 45344 | U14: 45358 | V14: Y | W14: =J14+14 -> 45367
A15: 2023.11.6 | C15: COSU8045938400 | D15: FSCU8884988 | G15: COSCO | H15: JIN LONG 689 329S | I15: 45282 | J15: 45355 | K15: SA-Adelaide | L15: 11-13 White Road, Gepps Cross SA 5094 | M15: Polyaire 10285 | Q15: 45287 | U15: 45359 | V15: Y | W15: =J15+14 -> 45369
A16: 2023.11.15 | C16: COSU8045938401 | D16: OOLU9349794 | G16: COSCO | H16: JIN RONG 02 / 078S | I16: 45282 | J16: 45355 | K16: SA-Adelaide | L16: 11-13 White Road, Gepps Cross SA 5094 | M16: Polyaire 16392 | Q16: 45287 | U16: 45358 | V16: Y | W16: =J16+14 -> 45369
A17: 2023.11.23 | C17: 712410076277 | D17: TSSU5110052 | G17: TSL | H17: TS SHEKOU 2401S | I17: 45350 | J17: 45365 | K17: QLD-Brisbane | L17: QLD Warehouse | M17: SAI ORD00000178 | Q17: 45356 | U17: 45371 | V17: Y | W17: =J17+21 -> 45386
A18: 2024.1.4 | C18: 712410074419 | D18: TRHU8701813 | G18: TSL | H18: TS SHEKOU 2401S | I18: 45350 | J18: 45372 | K18: Vic-Mel | L18: Mel Warehouse | M18: Odisee PO0051 | Q18: 45352 | U18: 45376 | V18: Y | W18: =J18+21 -> 45393
A19: 2024.1.9 | C19: 712410074464 | D19: TRHU8015855 | G19: TSL | H19: TS SHEKOU 2401S | I19: 45350 | J19: 45372 | K19: Vic-Mel | L19: Saving Earth | M19: Odisee PO0069 | Q19: 45352 | U19: 45374 | V19: Y | W19: =J19+21 -> 45393
A20: 2023.11.23 | C20: 712410083831 | D20: TSSU5000733 | G20: TSL | H20: TS SHEKOU 2401S | I20: 45350 | J20: 45372 | K20: Vic-Mel | L20: Mel Warehouse | M20: Part for Odisee Short-loaded | Q20: 45358 | U20: 45376 | V20: Y | W20: =J20+21 -> 45393
A21: 2024.1.17 | C21: COSU6378228180 | D21: OOLU9706150 | G21: COSCO | H21: COSCO HONG KONG 184S | I21: 45356 | J21: 45372 | K21: VIC-Mel | L21: Mel Warehouse | M21: - | Q21: 45367 | U21: 45374 | V21: Y | W21: =J21+21 -> 45393
A22: 2024.1.17 | C22: COSU6378228180 | D22: TGHU6924225 | G22: COSCO | H22: COSCO HONG KONG 184S | I22: 45356 | J22: 45372 | K22: VIC-Mel | L22: Mel Warehouse | M22: - | Q22: 45367 | U22: 45375 | V22: Y | W22: =J22+21 -> 45393
A23: 2024.1.17 | C23: COSU6378228180 | D23: CAAU6128066 | G23: COSCO | H23: COSCO HONG KONG 184S | I23: 45356 | J23: 45372 | K23: VIC-Mel | L23: Mel Warehouse | M23: Odisee PO0070 | Q23: 45367 | U23: 45374 | V23: Y | W23: =J23+21 -> 45393
A24: 2024.1.17 | C24: COSU6378228180 | D24: CSNU6622758 | G24: COSCO | H24: COSCO HONG KONG 184S | I24: 45356 | J24: 45372 | K24: VIC-Mel | L24: Mel Warehouse | M24: - | Q24: 45367 | U24: 45376 | V24: Y | W24: =J24+21 -> 45393
A25: 2024.1.9 | C25: 712410076406 | D25: TSSU5079194 | G25: TSL | H25: TS SHEKOU 2401S | I25: 45350 | J25: 45372 | K25: Vic-Mel | L25: Saving Earth | M25: Odisee PO0070 | Q25: 45352 | U25: 45376 | V25: Y | W25: =J25+21 -> 45393
A26: 2024.1.12 | C26: 712410102792 | D26: TEMU7935496 | G26: TSL | H26: KOTA LIMA 0015S | I26: 45357 | J26: 45376 | K26: Vic-Mel | L26: Mel Warehouse | M26: - | Q26: 45363 | U26: 45383 | V26: Y | W26: =J26+21 -> 45397
A27: 2024.1.12 | C27: 712410102815 | D27: TSSU5087374 | G27: TSL | H27: KOTA LIMA 0015S | I27: 45357 | J27: 45376 | K27: VIC-Mel | L27: Mel Warehouse | M27: - | Q27: 45362 | U27: 45381 | V27: Y | W27: =J27+21 -> 45397
A28: 2024.1.17 | C28: OOLU2146640990 | D28: OOCU8176764 | G28: OOCL | H28: COSCO HONG KONG / 184S | I28: 45356 | J28: 45377 | K28: QLD-Brisbane | L28: QLD Warehouse | M28: - | Q28: 45362 | U28: 45379 | V28: Y | W28: =J28+21 -> 45398
... A48: 2024.2.17 | C48: 712410155217 | D48: TIIU4454937 | G48: TSL | H48: KOTA MAKMUR 0318S | I48: 45382 | J48: 45402 | K48: VIC-Mel | L48: Mel Warehouse | M48: - | Q48: 45387 | U48: 45403 | V48: Y | W48: =J48+21 -> 45423
A49: 2024.2.17 | C49: ZIMUGZH0379364 | D49: ZCSU7140220 | G49: ZIM | H49: MARIANNA I/8/S | I49: 45390 | J49: 45406 | K49: VIC-Mel | L49: Mel Warehouse | M49: - | Q49: 45400 | U49: 45411 | V49: Y | W49: =J49+14 -> 45420
A50: 2024.2.23 | C50: 712410174652 | D50: TRHU8707447 | G50: TSL | H50: NORTHERN DISCOVERY 24003S | I50: 45389 | J50: 45407 | K50: VIC-Mel | L50: Mel Warehouse | M50: - | Q50: 45393 | U50: 45412 | V50: Y | W50: =J50+21 -> 45428
A51: 2024.2.22 | C51: 712410176946 | D51: TCNU6590893 | G51: TSL | H51: NORTHERN DISCOVERY 24003S | I51: 45389 | J51: 45407 | K51: VIC-Mel | M51: Odisee PO 0122+Odisee PO0093 | Q51: 45391 | U51: 45412 | V51: Y | W51: =J51+21 -> 45428
A52: 2024.1.30 | C52: HUSP40020500 | D52: PCIU9370500 | G52: PIL | H52: NORTHERN DISCOVERY 24003S | I52: 45389 | J52: 45407 | K52: VIC-Mel | L52: QLD Warehouse | M52: Odisee PO 0123 | Q52: 45391 | U52: 45412 | V52: Y | W52: =J52+14 -> 45421
A53: - | C53: CGZMF240300645 | D53: TLLU3365098 | G53: CTS | H53: NORTHERN DISCOVERY 24003S | I53: 45389 | J53: 45407 | K53: NSW-Sydney | L53: - | M53: ARBS Samples | Q53: 45397 | U53: 45413 | V53: Y | W53: =J53+14 -> 45421
A54: 2024.1.25 | C54: OOLU2147185530 | D54: GCXU5457857 | G54: OOCL | H54: GONG HUA V.240403 | I54: 45385 | J54: 45411 | K54: WA-Frementle | L54: 61 Conquest Way, Wangara WA 6065 | M54: Polyaire PO#: 19841 | Q54: 45393 | U54: 45418 | V54: Y | W54: =J54+14 -> 45425
A55: 2024.2.22 | C55: 712410173112 | D55: TCKU7567466 | G55: TSL | H55: TS CHENNAI 2402S | I55: 45396 | J55: 45411 | K55: VIC-Mel | L55: QLD Warehouse | M55: - | Q55: 45397 | U55: 45415 | V55: Y | W55: =J55+21 -> 45432
A56: 2024.2.22 | C56: 712410176960 | D56: MAGU5620082 | G56: TSL | H56: TS CHENNAI 2402S | I56: 45396 | J56: 45411 | K56: VIC-Mel | L56: QLD Warehouse | M56: - | Q56: 45397 | U56: 45415 | V56: Y | W56: =J56+21 -> 45432
A57: 2024.2.22 | C57: 712410179602 | D57: TEMU7738310 | G57: TSL | H57: TS CHENNAI 2402S | I57: 45396 | J57: 45411 | K57: VIC-Mel | L57: QLD Warehouse | M57: - | Q57: 45397 | U57: 45415 | V57: Y | W57: =J57+21 -> 45432
A58: 2024.2.22 | C58: 712410179626 | D58: TEMU7955390 | G58: TSL | H58: TS CHENNAI 2402S | I58: 45396 | J58: 45411 | K58: VIC-Mel | L58: QLD Warehouse | M58: - | Q58: 45397 | U58: 45415 | V58: Y | W58: =J58+21 -> 45432
A59: 2024.2.22 | C59: ZIMUGZH0380497 | D59: TEMU7418132 | G59: ZIM | H59: DANUBE 5/S | I59: 45396 | J59: 45412 | K59: VIC-Mel | L59: QLD Warehouse | M59: - | O59: 13652.12 | Q59: 45397 | U59: 45418 | V59: Y | W59: =J59+14 -> 45426
A60: 2024.2.22 | C60: ZIMUGZH0380755 | D60: FSCU8096970 | G60: ZIM | H60: DANUBE 5/S | I60: 45396 | J60: 45412 | K60: VIC-Mel | L60: QLD Warehouse | M60: - | Q60: 45397 | U60: 45418 | V60: Y | W60: =J60+14 -> 45426
A61: 2024.2.22 | C61: COSU6381013610 | D61: CCLU7453612 | G61: COSCO | H61: HENG JI 36 176S | I61: 45392 | J61: 45416 | K61: VIC-Mel | L61: QLD Warehouse | M61: - | Q61: 45397 | U61: 45419 | V61: Y | W61: =J61+21 -> 45437
A62: 2024.2.22 | C62: COSU6381013610 | D62: CSNU7037845 | G62: COSCO | H62: HENG JI 36 176S | I62: 45392 | J62: 45416 | K62: VIC-Mel | L62: QLD Warehouse | M62: - | Q62: 45397 | U62: 45419 | V62: Y | W62: =J62+21 -> 45437
A63: 2024.2.17 | C63: 712410175932 | D63: CAIU4967475 | G63: TSL | H63: NORTHERN DISCOVERY 24003S | I63: 45389 | J63: 45418 | K63: QLD-Brisbane | L63: QLD Warehouse | M63: - | Q63: 45400 | U63: 45426 | V63: Y | W63: =J63+21 -> 45439
A64: 2024.2.17 | C64: 712410191895 | D64: TCKU6750446 | G64: TSL | H64: NORTHERN DISCOVERY 24003S | I64: 45389 | J64: 45418 | K64: QLD-Brisbane | L64: QLD Warehouse | M64: - | Q64: 45393 | U64: 45426 | V64: Y | W64: =J64+21 -> 45439
A65: 2024.2.17 | C65: ZIMUGZH0385802 | D65: SEGU5330977 | G65: ZIM | H65: GANGES 3/S | I65: 45408 | J65: 45419 | K65: QLD-Brisbane | L65: QLD Warehouse | M65: - | Q65: 45415 | U65: 45427 | V65: Y | W65: =J65+14 -> 45433
A66: 2024.2.17 | C66: ZIMUGZH0385804 | D66: GAOU6455219 | G66: ZIM | H66: GANGES 3/S | I66: 45408 | J66: 45419 | K66: QLD-Brisbane | L66: QLD Warehouse | M66: - | Q66: 45412 | U66: 45427 | V66: Y | W66: =J66+14 -> 45433
A67: 2024.2.8 | C67: COSU6381867090 | D67: SEGU6663400 | G67: COSCO | H67: GONG HUA 352S | I67: 45398 | J67: 45425 | K67: WA-Frementle | L67: 61 Conquest Way, Wangara WA 6065 | M67: Polyaire PO#: 20627 | Q67: 45410 | U67: 45433 | V67: Y | W67: =J67+14 -> 45439
A68: 2024.2.17 | C68: 712410219278 | D68: TCKU7564045 | G68: TSL | H68: KOTA GADANG 0224S | I68: 45403 | J68: 45428 | K68: QLD-Brisbane | L68: QLD Warehouse | M68: - | Q68: 45410 | U68: 45433 | V68: Y | W68: =J68+21 -> 45449
A69: 2024.2.17 | C69: YMJAA221015681 | D69: YMMU6719067 | G69: YML | H69: KOTA GADANG 0224S | I69: 45403 | J69: 45428 | K69: QLD-Brisbane | L69: QLD Warehouse | M69: - | Q69: 45411 | U69: 45434 | V69: Y | W69: =J69+14 -> 45442
A70: 2024.2.17 | C70: YMJAA221015731 | D70: YMLU8930882 | G70: YML | H70: KOTA GADANG 0224S | I70: 45403 | J70: 45428 | K70: QLD-Brisbane | L70: QLD Warehouse | M70: - | Q70: 45410 | U70: 45433 | V70: Y | W70: =J70+14 -> 45442
A71: 2024.1.25 | C71: OOLU2147185550 | D71: OOCU8759313 | G71: OOCL | H71: GONG HUA V.240403 | I71: 45385 | J71: 45429 | K71: SA-Adelaide | L71: 11-13 White Road, Gepps Cross SA 5094 | M71: Polyaire PO#: 19855 | Q71: 45393 | U71: 45433 | V71: Y | W71: =J71+14 -> 45443
A72: 2024.1.4 | C72: 721410484722 | D72: TLLU8816893 | G72: TSL | H72: EVER USEFUL 176S | I72: 45409 | J72: 45429 | K72: QLD-Brisbane | L72: QLD Warehouse | M72: - | Q72: 45413 | U72: 45434 | V72: Y | W72: =J72+14 -> 45443
A73: 2024.3.11 | C73: 712410274239 | D73: TLLU7974702 | G73: TSL | H73: YM ETERNITY 121S | I73: 45420 | J73: 45437 | K73: Vic-Mel | L73: Mel Warehouse | M73: - | Q73: 45423 | U73: 45441 | V73: Y | W73: =J73+21 -> 45458
A74: 2024.3.7 | C74: COSU6383261220 | D74: OOCU7561977 | G74: COSCO | H74: JOGELA 194S | I74: 45420 | J74: 45438 | K74: Vic-Mel | L74: Mel Warehouse | M74: - | Q74: 45428 | U74: 45442 | V74: Y | W74: =J74+21 -> 45459
A75: 2024.2.17 | C75: OOLU2147378680 | D75: OOCU6523334 | G75: OOCL | H75: COSCO SINGAPORE 179S | I75: 45416 | J75: 45438 | K75: QLD-Brisbane | L75: QLD Warehouse | M75: - | Q75: 45421 | U75: 45442 | V75: Y | W75: =J75+21 -> 45459
A76: 2024.1.17 | C76: 712410266142 | D76: TXGU7367188 | G76: TSL | H76: YM ETERNITY 121S | I76: 45420 | J76: 45442 | K76: QLD-Brisbane | L76: QLD Warehouse | M76: - | Q76: 45423 | U76: 45448 | V76: Y | W76: =J76+21 -> 45463
A77: 2024.2.26 | C77: 712410261314 | D77: TRHU4082027 | G77: TSL | H77: YM ETERNITY 121S | I77: 45420 | J77: 45442 | K77: QLD-Brisbane | M77: Polyaire PO#: 21627 | Q77: 45423 | U77: 45450 | V77: Y | W77: =J77+21 -> 45463
A78: 2024.1.4 | C78: 721410610756 | D78: TXGU5748570 | G78: TSL | H78: TIAN SHUN HE 2402S | I78: 45428 | J78: 45442 | K78: Vic-Mel | L78: Mel Warehouse | M78: - | Q78: 45432 | U78: 45449 | V78: Y | W78: =J78+14 -> 45456
A79: 2024.2.17 | C79: 712410283811 | D79: TXGU7374274 | G79: TSL | H79: KOTA MAKMUR 0319S | I79: 45428 | J79: 45445 | K79: Vic-Mel | L79: Mel Warehouse | M79: - | Q79: 45431 | U79: 45448 | V79: Y | W79: =J79+21 -> 45466
A80: 2024.2.17 | C80: 712410281008 | D80: TSSU5122705 | G80: TSL | H80: KOTA MAKMUR 0319S | I80: 45428 | J80: 45445 | K80: Vic-Mel | L80: Mel Warehouse | M80: - | Q80: 45431 | U80: 45448 | V80: Y | W80: =J80+21 -> 45466
A81: 2024.3.11 | C81: 712410283828 | D81: TSSU5172521 | G81: TSL | H81: KOTA MAKMUR 0319S | I81: 45428 | J81: 45445 | K81: Vic-Mel | L81: Saving Earth - 1/22 Rockfield Way, Ravenhall | M81: - | Q81: 45431 | U81: 45448 | V81: Y | W81: =J81+21 -> 45466
A82: 2024.2.17 | C82: 712410285440 | D82: TRHU8448881 | G82: TSL | H82: KOTA MAKMUR 0319S | I82: 45428 | J82: 45445 | K82: Vic-Mel | L82: Mel Warehouse | M82: - | Q82: 45431 | U82: 45448 | V82: Y | W82: =J82+21 -> 45466
A83: 2024.1.29 | C83: 712410280995 | D83: TRHU4083698 | G83: TSL | H83: KOTA MAKMUR 0319S | I83: 45428 | J83: 45445 | K83: Vic-Mel | L83: Mel Warehouse | M83: - | Q83: 45431 | U83: 45448 | V83: Y | W83: =J83+21 -> 45466
A84: 2024.2.28 | C84: COSU6383434030 | D84: CBHU9025465 | G84: COSCO | H84: CSCL ATLANTIC OCEAN 053W | I84: 45428 | J84: 45453 | K84: WA-Frementle | L84: 61 Conquest Way, Wangara WA 6065 | M84: Polyaire PO#: 21766 | Q84: 45433 | U84: 45456 | V84: Y | W84: =J84+14 -> 45467
A85: 2024.4.29 | C85: ZIMUGZH0391193 | D85: TIIU4521444 | G85: ZIM | H85: MARIANNA I 9/S | I85: 45437 | J85: 45454 | K85: Vic-Mel | L85: Mel Warehouse | M85: - | Q85: 45446 | U85: 45460 | V85: Y | W85: =J85+14 -> 45468
A86: 2024.3.11 | C86: ZIMUGZH0390330 | D86: ZCSU7746711 | G86: ZIM | H86: DANUBE 6/S | I86: 45443 | J86: 45455 | K86: QLD-Brisbane | L86: QLD Warehouse | M86: - | Q86: 45447 | U86: 45460 | V86: Y | W86: =J86+14 -> 45469
A87: 2024.3.26 | C87: MEDUQS234555 | D87: MSMU4411670 | G87: MSC | H87: MARIANNA I - KQ419A | I87: 45438 | J87: 45455 | K87: Vic-Mel | L87: SAVING EARTH - 1/22 Rockfield Way, Ravenhall | M87: - | Q87: 45443 | U87: 45461 | V87: Y | W87: =J87+14 -> 45469
A88: 2024.3.11 | C88: MEDUQS234563 | D88: MSMU8743170 | G88: MSC | H88: MARIANNA I - KQ419A | I88: 45438 | J88: 45455 | K88: Vic-Mel | L88: Mel Warehouse | M88: - | Q88: 45446 | U88: 45460 | V88: Y | W88: =J88+14 -> 45469
A89: 2024.3.11 | C89: MEDUQS213559 | D89: TCNU8143894 | G89: MSC | H89: MARIANNA I - KQ419A | I89: 45438 | J89: 45455 | K89: Vic-Mel | L89: Mel Warehouse | M89: - | Q89: 45447 | U89: 45460 | V89: Y | W89: =J89+14 -> 45469
A90: 2024.2.12 | C90: COSU6384267980 | D90: GCXU5476559 | G90: COSCO | H90: JIN RONG 02 092S | I90: 45427 | J90: 45456 | K90: Vic-Mel | M90: Polyaire PO#: 20772 | Q90: 45437 | U90: 45460 | V90: Y | W90: =J90+21 -> 45477
A91: 2024.4.29 | C91: 721410696736 | D91: GAOU7093984 | G91: TSL | H91: TS SYDNEY 2403S | I91: 45442 | J91: 45457 | K91: Vic-Mel | L91: Mel Warehouse | M91: - | Q91: 45447 | U91: 45464 | V91: Y | W91: =J91+14 -> 45471
A92: 2024.4.29 | C92: ZIMUGZH0387230 | D92: TIIU4521660 | G92: ZIM | H92: DANUBE 6/S | I92: 45443 | J92: 45458 | K92: Vic-Mel | L92: Mel Warehouse | M92: - | Q92: 45446 | U92: 45462 | V92: Y | W92: =J92+14 -> 45472
A93: 2024.3.11 | C93: ZIMUGZH0389575 | D93: TCNU5802112 | G93: ZIM | H93: DANUBE 6/S | I93: 45443 | J93: 45458 | K93: Vic-Mel | L93: Mel Warehouse | M93: - | Q93: 45447 | U93: 45462 | V93: Y | W93: =J93+14 -> 45472
A94: 2024.2.17 | C94: COSU6382252130 | D94: FFAU2608590 | G94: COSCO | H94: CSCL MERCURY 092W | I94: 45405 | J94: 45460 | K94: SA-Adelaide | L94: 11-13 White Road, Gepps Cross SA 5094 | M94: - | Q94: 45410 | U94: 45467 | V94: Y | W94: =J94+14 -> 45474
A95: 2024.3.11 | C95: COSU6385086220 | D95: SEKU4561955 | G95: COSCO | H95: HONG AN TAI 188 388S | I95: 45439 | J95: 45463 | K95: Vic-Mel | L95: Mel Warehouse | M95: - | Q95: 45447 | U95: 45467 | V95: Y | W95: =J95+21 -> 45484
A96: 2024.5.7 | C96: OOLU2148622760 | D96: CSNU6009582 | G96: OOCL | H96: OOCL KUALA LUMPUR 171S | I96: 45447 | J96: 45463 | K96: Vic-Mel | L96: 3/3-5 Weddel Court, Laverton North | Q96: 45449 | U96: 45467 | V96: Y | W96: =J96+21 -> 45484
A97: 2024.5.7 | C97: OOLU2148622760 | D97: CSNU7744339 | G97: OOCL | H97: OOCL KUALA LUMPUR 171S | I97: 45447 | J97: 45463 | K97: Vic-Mel | L97: 3/3-5 Weddel Court, Laverton North | Q97: 45449 | U97: 45467 | V97: Y | W97: =J97+21 -> 45484
A98: 2024.3.11 | C98: 712410321803 | D98: FFAU4382964 | G98: TSL | H98: TS CHENNAI 2403S | I98: 45445 | J98: 45464 | K98: Vic-Mel | L98: Saving Earth - 1/22 Rockfield Way, Ravenhall | M98: - | Q98: 45449 | U98: 45467 | V98: Y | W98: =J98+21 -> 45485
A99: 2024.3.11 | C99: 712410321841 | D99: SEKU4079141 | G99: TSL | H99: TS CHENNAI 2403S | I99: 45445 | J99: 45464 | K99: Vic-Mel | L99: Mel Warehouse | M99: - | Q99: 45449 | U99: 45468 | V99: Y | W99: =J99+21 -> 45485
A100: 2024.3.11 | C100: 712410321773 | D100: TRHU8009739 | G100: TSL | H100: TS CHENNAI 2403S | I100: 45445 | J100: 45464 | K100: Vic-Mel | L100: Mel Warehouse | M100: - | Q100: 45449 | U100: 45469 | V100: Y | W100: =J100+21 -> 45485
A101: 2024.3.11 | C101: 712410321834 | D101: TXGU7374968 | G101: TSL | H101: TS CHENNAI 2403S | I101: 45445 | J101: 45464 | K101: Vic-Mel | L101: Saving Earth - 1/22 Rockfield Way, Ravenhall | M101: - | Q101: 45449 | U101: 45470 | V101: Y | W101: =J101+21 -> 45485
A102: 2024.4.29 | C102: 712410321827 | D102: TRHU8709671 | G102: TSL | H102: TS CHENNAI 2403S | I102: 45445 | J102: 45464 | K102: Vic-Mel | L102: Mel Warehouse | M102: - | Q102: 45447 | U102: 45468 | V102: Y | W102: =J102+21 -> 45485
A103: 2024.5.7 | C103: 712410346103 | D103: TXGU5977772 | G103: TSL | H103: KOTA GADANG 0225S | I103: 45450 | J103: 45465 | K103: Vic-Mel | L103: Mel Warehouse | M103: - | Q103: 45456 | U103: 45471 | V103: Y | W103: =J103+14 -> 45479
A104: / | C104: SNLEBJALA22102 | D104: WSDU4982360 | G104: SNL | H104: DAFENG3026 240531S | I104: 45443 | J104: 45467 | K104: Vic-Mel | L104: Mel Warehouse | M104: - | Q104: 45454 | U104: 45474 | V104: Y | W104: =J104+21 -> 45488
A105: 2024.4.29 | C105: 721410696644 | D105: GAOU6735987 | G105: TSL | H105: TS SYDNEY 2403S | I105: 45442 | J105: 45468 | K105: QLD-Brisbane | L105: QLD Warehouse | M105: - | Q105: 45447 | U105: 45471 | V105: Y | W105: =J105+14 -> 45482
A106: 2024.2.17 | C106: ULCGZ2405009 | D106: YMLU8762958 | G106: YML | H106: TS SYDNEY/2403S | I106: 45442 | J106: 45468 | K106: QLD-Brisbane | L106: QLD Warehouse | M106: - | Q106: 45450 | U106: 45471 | V106: Y | W106: =J106+14 -> 45482
A107: 2024.3.11 | C107: 712410321742 | D107: TRHU8022303 | G107: TSL | H107: TS CHENNAI 2403S | I107: 45445 | J107: 45469 | K107: QLD-Brisbane | L107: QLD Warehouse | M107: - | Q107: 45449 | U107: 45475 | V107: Y | W107: =J107+21 -> 45490
A108: 2024.4.17 | C108: 712410372560 | D108: TLLU8716847 | G108: TSL | H108: TS COLOMBO 2405S | I108: 45455 | J108: 45470 | K108: NSW-Sydney | M108: Polyaire PO#: 24172 | Q108: 45456 | U108: 45476 | V108: Y | W108: =J108+21 -> 45491
A109: 2024.4.29 | C109: 721410799185 | D109: TEMU7769559 | G109: TSL | H109: EVER USEFUL 177S | I109: 45456 | J109: 45470 | K109: Vic-Mel | L109: Mel Warehouse | M109: - | Q109: 45460 | U109: 45476 | V109: Y | W109: =J109+14 -> 45484
A110: 2024.4.29 | C110: 721410799185 | D110: TXGU6748554 | G110: TSL | H110: EVER USEFUL 177S | I110: 45456 | J110: 45470 | K110: Vic-Mel | L110: Mel Warehouse | M110: - | Q110: 45460 | U110: 45476 | V110: Y | W110: =J110+14 -> 45484
A111: 2024.2.17 | C111: MEDUQS250049 | D111: MSDU5496819 | G111: MSC | H111: DANUBE - 6S | I111: 45443 | J111: 45471 | K111: Vic-Mel | L111: Mel Warehouse | M111: - | Q111: 45449 | U111: 45475 | V111: Y | W111: =J111+14 -> 45485
A112: 2024.3.11 | C112: MEDUQS250031 | D112: MSMU5921663 | G112: MSC | H112: DANUBE - 6S | I112: 45443 | J112: 45471 | K112: Vic-Mel | L112: Saving Earth 1/22 Rockfield Way, Ravenhall VIC 3023 | M112: Odisee BO019 | Q112: 45449 | U112: 45475 | V112: Y | W112: =J112+14 -> 45485
A113: 2024.4.29 | C113: 712410372652 | D113: CAIU4647912 | G113: TSL | H113: TS COLOMBO 2405S | I113: 45455 | J113: 45473 | K113: Vic-Mel | L113: 1/162 Australis Drive, Derrimut, VIC | M113: Chromogen PO#: 505185 | Q113: 45456 | U113: 45476 | V113: Y | W113: =J113+21 -> 45494
A114: 2024.5.15 | C114: 712410382019 | D114: TLLU8716533 | G114: TSL | H114: TS COLOMBO 2405S | I114: 45455 | J114: 45473 | K114: Vic-Mel | L114: 1/162 Australis Drive, Derrimut, VIC | M114: Chromogen PO#: 507523 | Q114: 45456 | U114: 45475 | V114: Y | W114: =J114+21 -> 45494
A115: 2024.4.19 | C115: 712410382033 | D115: TRHU8715360 | G115: TSL | H115: TS COLOMBO 2405S | I115: 45455 | J115: 45473 | K115: Vic-Mel | L115: 3/3-5 Weddel Court, Laverton North | M115: - | Q115: 45456 | U115: 45477 | V115: Y | W115: =J115+21 -> 45494
A116: 2024.5.17 | C116: 712410382026 | D116: TXGU5775046 | G116: TSL | H116: TS COLOMBO 2405S | I116: 45455 | J116: 45473 | K116: Vic-Mel | L116: 3/3-5 Weddel Court, Laverton North | M116: - | Q116: 45460 | U116: 45477 | V116: Y | W116: =J116+21 -> 45494
A117: 2024.5.9 | C117: 712410382002 | D117: TSSU5157912 | G117: TSL | H117: TS COLOMBO 2405S | I117: 45455 | J117: 45473 | K117: Vic-Mel | L117: 3/3-5 Weddel Court, Laverton North | M117: - | Q117: 45464 | U117: 45478 | V117: Y | W117: =J117+21 -> 45494
A118: 2024.3.15 | C118: COSU6385478480 | D118: OOCU7353382 | G118: COSCO | H118: OOCL TAIPEI 076W | I118: 45442 | J118: 45473 | K118: WA-Frementle | L118: 61 Conquest Way, Wangara WA 6065 | M118: Polyaire PO#: 22669 | Q118: 45456 | U118: 45478 | V118: Y | W118: =J118+14 -> 45487
A119: 2024.4.26 | C119: COSU6385500750 | D119: CBHU9172131 | G119: COSCO | H119: XIN YA ZHOU 162W | I119: 45449 | J119: 45473 | K119: WA-Frementle | L119: 11 Spencer Street, Cockburn Central WA 6164 | M119: Polyaire PO #23400 | Q119: 45456 | U119: 45478 | V119: Y | W119: =J119+14 -> 45487
...

Sheet SP
A1: PO No. | B1: Ctn No. | C1: Factory Code | D1: Description | E1: QTY | F1: INV. NO | G1: Destination | H1: ETA | I1: Remark
A2: - | B2: TSSU5194515 | C2: 90GP095 | D2: 90GP095 Gas Cooktop | E2: 1 | F2: MDWZB241028D0003 | G2: VIC-Mel | H2: 45617 | I2: KWHA MAZ Sample
C3: 60GJ084 | D3: 60GJ084 Gas Cooktop | E3: 1 | F3: MDWZB241028D0003 | G3: VIC-Mel
C4: 30GB095 | D4: 30GB095 Gas Cooktop | E4: 1 | F4: MDWZB241028D0003 | G4: VIC-Mel
C5: 75GP095 | D5: 75GP095 Gas Cooktop | E5: 1 | F5: MDWZB241028D0003 | G5: VIC-Mel
C6: 60SL403 | D6: 60SL403 Gas Cooktop | E6: 1 | F6: MDWZB241028D0003 | G6: VIC-Mel
C7: 75SP021 | D7: 75SP021 Gas Cooktop | E7: 1 | F7: MDWZB241028D0003 | G7: VIC-Mel
C8: - | D8: DISHWASHER | E8: 1 | F8: MDWZB241028D0003 | G8: VIC-Mel
C9: - | D9: VALVE | E9: 200 | F9: MDWZB241028D0003 | G9: VIC-Mel | I9: FOC，MWPU4W的阀体
A10: KWHA 27_08_24 | B10: TSSU5063562 | C10: 17476000007431 | D10: Heating Tube Assembly | E10: 10 | F10: MDWDB241107D0001 | G10: VIC-Mel | H10: 45630
A11: SR240923023 | C11: 11201007003440 | D11: Room Temperature Sensor | E11: 1 | F11: MDCAS2411070005P | G11: VIC-Mel | I11: MBT Quality Claim-7月
A12: SR240923023 | C12: 17122300007572 | D12: Indoor Unit Main Control Board | E12: 1 | F12: MDCAS2411070005P | G12: VIC-Mel
A13: SR240904009 | C13: 17127000012938 | D13: Outdoor main control board assembly | E13: 2 | F13: MDCAS2411070005P | G13: VIC-Mel
A14: - | C14: 11001010000063 | D14: Induction Pump | E14: 20 | F14: MDAJB241107D0006 | G14: VIC-Mel | I14: RAC Q4支持配件
C15: 11002015003981 | D15: Brushless DC Motor | E15: 8 | F15: MDAJB241107D0006 | G15: VIC-Mel
C16: 11002015009825 | D16: Brushless DC Motor | E16: 26 | F16: MDAJB241107D0006 | G16: VIC-Mel
C17: 11002015008264 | D17: Brushless DC Motor | E17: 10 | F17: MDAJB241107D0006 | G17: VIC-Mel
C18: 11002015003861 | D18: Brushless DC Motor | E18: 10 | F18: MDAJB241107D0006 | G18: VIC-Mel
C19: 11002015000366 | D19: Brushless DC Motor | E19: 20 | F19: MDAJB241107D0006 | G19: VIC-Mel
C20: 11002015018478 | D20: Brushless DC Motor | E20: 5 | F20: MDAJB241107D0006 | G20: VIC-Mel
C21: 11002015002521 | D21: Brushless DC Motor | E21: 10 | F21: MDAJB241107D0006 | G21: VIC-Mel
C22: 11002015000187 | D22: Brushless DC Motor | E22: 4 | F22: MDAJB241107D0006 | G22: VIC-Mel
C23: 11002010000143 | D23: Stepper Motor | E23: 30 | F23: MDAJB241107D0006 | G23: VIC-Mel
C24: 11002015000051 | D24: Brushless DC Motor | E24: 15 | F24: MDAJB241107D0006 | G24: VIC-Mel
C25: 11002015000150 | D25: Brushless DC Motor | E25: 15 | F25: MDAJB241107D0006 | G25: VIC-Mel
C26: 11002015000247 | D26: Brushless DC Motor | E26: 7 | F26: MDAJB241107D0006 | G26: VIC-Mel
... C87: 17401204017449 | D87: LV Junction Cable Subassembly | E87: 40 | F87: MDAJB241107D0006 | G87: VIC-Mel
A88: - | B88: BSIU9814155 | C88: 17122000A18354 | D88: Outdoor main control board subassembly | E88: 5 | F88: MDAJB241126D0010 | G88: VIC-Mel | H88: 45648 | I88: RAC 售后支持配件，FOC
A89: RAC_01_11_24 | C89: 12122000025627 | D89: Panel Frame Assembly | E89: 1 | F89: MDAJB241126D0009 | G89: VIC-Mel
A90: MBT_09_12_24 | B90: GAOU6740052 | C90: 17122300003794 | D90: Outdoor Main Control Board Assembly | E90: 1 | F90: MDCAS250103001200001 | G90: QLD-Brisbane | H90: 45678 | I90: 售后-Compact PO 00000314
A91: - | B91: TSSU5116615 | C91: 12566200A19238 | D91: Glass Panel Assembly | E91: 3 | F91: MDWZB250118D0005 | G91: VIC-Mel | H91: 45708 | I91: KWHA 售后FOC配件
A92: KWHA_13_12_24 | C92: 15663200A09024 | D92: Water purifier filter MWPU1W | E92: 12 | F92: MDWJB250117D0006 | G92: VIC-Mel
A93: PINBRI20241210002 | C93: - | D93: MFAG80VA-W | E93: 1 | F93: MDAJB250117D0014 | G93: VIC-Mel | I93: Aftersales. RAC铭牌
A94: PINBRI20241210002 | C94: - | D94: MFAG20VA-N | E94: 30 | F94: MDAJB250117D0014
A95: PINBRI20241210002 | C95: - | D95: MFAG20VA-W | E95: 30 | F95: MDAJB250117D0014
A96: PINBRI20241210002 | C96: - | D96: MFAG60VA-N | E96: 40 | F96: MDAJB250117D0014
A97: PINBRI20241210002 | C97: - | D97: MFAG60VA-W | E97: 40 | F97: MDAJB250117D0014
A98: PINBRI20241210002 | C98: - | D98: MFAG51VA-N | E98: 15 | F98: MDAJB250117D0014
A99: PINBRI20241210002 | C99: - | D99: MFAG51VA-W | E99: 15 | F99: MDAJB250117D0014
A100: PINBRI20241210002 | C100: - | D100: MFAB90NB | E100: 2 | F100: MDAJB250117D0014
A101: 2024.11.25 | C101: 12100102000044 | D101: 贯流风轮 RoHS,REACH GL-94*605-N | E101: 10 | F101: MDAJS2501200024 | G101: VIC-Mel | I101: RAC品质问题一次性赔付-折换配件
A102: 2024.11.25 | C102: 17122000A41190 | D102: 变频模块组件(室外) RoHS US1-KFR140W/BP3T1N1-E30(PS21A79+STK760-216+ATQ420D1UMU).JD.TY.MMK.MK(SHSJ) 带散热器散件 售后专用 | E102: 4 | F102: MDAJS2501200024 | G102: VIC-Mel
A103: 2024.11.25 | C103: 17122000054487 | D103: 变频模块组件(室外) RoHS AU-KFR80W/BP3N8-D30(C5)-GW.D.13.MK2.10 | E103: 6 | F103: MDAJS2501200024 | G103: VIC-Mel
A104: 2024.11.25 | C104: 17122000039528 | D104: 变频模块组件(室内) RoHS DCFan(MN103DF46XEA+PS219C4+LNK306DG).JD.TY.MMK.MK3.9 单风机、55W电机、200毫欧电阻、R32冷媒 | E104: 5 | F104: MDAJS2501200024 | G104: VIC-Mel
A105: 2024.11.25 | C105: 17122300004732 | D105: 一拖多变频室外主控板组件 RoHS AU-KFR71W/BP3T3N8-X430 M3OA-24HFN8-Q.JD.FW2.XWKB.WK2.1(DR) | E105: 5 | F105: MDAJS2501200024 | G105: VIC-Mel
A106: 2024.11.25 | C106: 17122000056150 | D106: 变频模块组件(室外) RoHS AU-KFR120W/BP3T5N8（KTF310D43UMT）-D31.D.13.MK2.1 | E106: 5 | F106: MDAJS2501200024 | G106: VIC-Mel
A107: 2024.11.25 | C107: 17122500002531 | D107: 轻商嵌入式室内主控板组件 RoHS AU-KFR105Q4/BP3N1Y-D(C3)-W-[N].JD.Q.NK.NK2.1 达温吹设定风 | E107: 5 | F107: MDAJS2501200024 | G107: VIC-Mel
A108: 2024.11.25 | C108: 17122000054489 | D108: 外销变频室外主控板组件 RoHS AU-KFR90W/BP3N8-D30(C5)-GW(PAIQI).ZD.JFW.WXWK2.WK2.10 | E108: 5 | F108: MDAJS2501200024 | G108: VIC-Mel
A109: 2024.11.25 | C109: 17122300003087 | D109: 一拖多变频室外主控板组件 RoHS AU-KFR80W/BP3T4N1-D30(PAIQI).JD.FW.WXWKB.WK2.1 | E109: 4 | F109: MDAJS2501200024 | G109: VIC-Mel
A110: 2024.11.25 | C110: 17122300004974 | D110: 一拖多变频室外主控板组件 RoHS AU-KFR80W/BP3T4N8-D30.ZY001.JD.FW2.XWKB.WK2-1 | E110: 5 | F110: MDAJS2501200024 | G110: VIC-Mel
A111: 2024.11.25 | C111: 17122000056152 | D111: 外销变频室外主控板组件 RoHS AU-KFR120W/BP3T5N8-D30(R32).ZJD.JFW.WXWKB.WK2.1 | E111: 5 | F111: MDAJS2501200024 | G111: VIC-Mel
A112: 2024.11.25 | C112: 17122000040411 | D112: 电源模块板组件 RoHS AU-KFR70W/HALT(DR+0.5W+R18).D.13.WK2.1 | E112: 20 | F112: MDAJS2501200024 | G112: VIC-Mel
A113: 2024.11.25 | C113: 17122000023878 | D113: 外销变频室外主控板组件 RoHS AU-KFR70W/BP3N1-D30(C3).JD.FW.WXWKB.WK2.2 | E113: 5 | F113: MDAJS2501200024 | G113: VIC-Mel
... A159: 2024.11.25 | C159: 17122000062261 | D159: 变频模块组件(室外) RoHS KFR160W/BP3T1N1-E30(FAN9673+SDM30M60AC+SLIMDIP-S).JD.TY.MMK.MK1.14 | E159: 20 | F159: MDAJS2501200024 | G159: VIC-Mel
A160: MBT_23_12_24 | B160: By Air: TNT 396019724 | C160: 22012900003431 | D160: T-MBQ1-02E | E160: 2 | F160: MDCASS21202502180240 | G160: VIC-Mel | H160: 45722 | I160: 去MEL仓库
A161: MBT_23_12_24 | C161: 22012900003270 | D161: T-MBQ4- 03f | E161: 2 | F161: MDCASS21202502180240 | G161: VIC-Mel | I161: For Melbourne showroom
A162: SR241219013 | C162: 15411600A00005 | D162: FQH-04A | E162: 2 | F162: MDCASS21202502180240 | G162: VIC-Mel | I162: MBT quality claim-11月VRF
A163: SR241219013 | C163: 15411600A00001 | D163: FQH-05A | E163: 3 | F163: MDCASS21202502180240 | G163: VIC-Mel
A164: RAC_08_01_25B | B164: BMOU5040163 | C164: 11001010000063 | D164: Induction Pump | E164: 5 | F164: MDAJB250215D0009 | G164: VIC-Mel | H164: 45724 | I164: 售后下单配件
A165: RAC_08_01_25B | C165: 12120600004203 | D165: Window Sealing Board | E165: 10 | F165: MDAWB250215D0005 | G165: VIC-Mel
A166: RAC_08_01_25B | C166: 12120600004204 | D166: Window Sealing Board | E166: 8 | F166: MDAWB250215D0005 | G166: VIC-Mel
A167: RAC_08_01_25B | C167: 17122000056152 | D167: Outdoor main control board subassembly | E167: 6 | F167: MDAJB250215D0009 | G167: VIC-Mel
A168: RAC_08_01_25B | C168: 17122000056150 | D168: Inverter module subassembly | E168: 6 | F168: MDAJB250215D0009 | G168: VIC-Mel
A169: - | C169: 17170000000440 | D169: Digital Display | E169: 1 | F169: MDOKB250215D0004 | G169: VIC-Mel | I169: MCA赔付售后配件，FOC
A170: 2410019V | B170: CSLU6027568 | C170: 17126000006190 | D170: Indoor Unit Main Control Board | E170: 1 | F170: MDCAS2502210019 | G170: VIC-Mel | H170: 45728 | I170: MBT quality claim-10月
A171: 2410028V | C171: 12122000031518 | D171: Panel Frame Assembly | E171: 2 | G171: VIC-Mel
A172: 2410028V | C172: 12126000003344 | D172: Panel assembly | E172: 2 | G172: VIC-Mel
A173: 2411005V | C173: 17126000006190 | D173: Indoor Unit Main Control Board | E173: 1 | G173: VIC-Mel | I173: MBT quality claim-11月
A174: 2411144V | C174: 17126000006190 | D174: Indoor Unit Main Control Board | E174: 1 | G174: VIC-Mel
A175: 2411005V | C175: 17122300007572 | D175: Indoor Unit Main Control Board | E175: 1 | G175: VIC-Mel
A176: 2411061V | C176: 17126000006190 | D176: Indoor Unit Main Control Board | E176: 1 | G176: VIC-Mel
A177: - | B177: SNBU8371630 | C177: 17401204023034 | D177: MBT PQE线 | E177: 420 | F177: MDCAS2502210029 | G177: VIC-Mel | H177: 45737 | I177: MBT赠送
A178: RAC_30_01_25 | B178: By Air: UPS 1ZG074H80414167416 | C178: 17220300A00277 | D178: Display box subassembly | E178: 50 | F178: MDAJBS10202503150004 | G178: VIC-Mel | H178: 45737 | I178: NCE
A179: MBT_24_02_25 | B179: - | C179: 16027000017650 | D179: MDV-V200WN1(AU) 铭牌 | E179: 20 | F179: MDCASS21202503260172 | G179: VIC-Mel | H179: 2025/4/31 | I179: RAC关总帮忙带到澳洲
A180: MBT_24_02_25 | C180: 16027000A75001 | D180: MDV-V230WN1(AU) 铭牌 | E180: 20 | F180: MDCASS21202503260172 | G180: VIC-Mel
A181: MBT_24_02_25 | C181: 16027000A76251 | D181: MDV-V235WN1(AU)-A 铭牌 | E181: 20 | F181: MDCASS21202503260172 | G181: VIC-Mel
A182: RAC_30_01_25 | B182: ONEU1009210 | C182: 17220300A00277 | D182: Display box subassembly | E182: 50 | F182: MDAJB250315D0008 | G182: VIC-Mel | H182: 45757 | I182: NCE
A183: MBT_18_12_24 | B183: JXLU6390272 | C183: 12100105000022 | D183: Axial Fan | E183: 6 | F183: MDCAS2503120010 | G183: VIC-Mel | H183: 45765 | I183: Aftersales Spare Part
A184: MBT_18_12_24 | C184: 15725300000783 | D184: Titanium Heat Exchanger Assembly | E184: 2 | F184: MDCAS2503120010 | G184: VIC-Mel
A185: MBT_18_12_24 | C185: 17400516000024 | D185: Pressure Controller | E185: 2 | F185: MDCAS2503120010 | G185: VIC-Mel
A186: MBT_18_12_24 | C186: 11002015000366 | D186: Brushless DC Motor | E186: 3 | F186: MDCAS2503120010 | G186: VIC-Mel
A187: MBT_18_12_24 | C187: 12125300002861 | D187: Waterproof Box Assembly | E187: 5 | F187: MDCAS2503120010 | G187: VIC-Mel
A188: MBT_18_12_24 | C188: 17125300004708 | D188: Inverter Module Assembly | E188: 3 | F188: MDCAS2503120010 | G188: VIC-Mel
A189: MBT_18_12_24 | C189: 11203103000145 | D189: Linear Transformer | E189: 5 | F189: MDCAS2503120010 | G189: VIC-Mel
A190: MBT_18_12_24 | C190: 17125300004709 | D190: Outdoor Main Control Board Assembly | E190: 5 | F190: MDCAS2503120010 | G190: VIC-Mel
A191: MBT_18_12_24 | C191: 17400401000026 | D191: Terminal Block | E191: 3 | F191: MDCAS2503120010 | G191: VIC-Mel
A192: MBT_18_12_24 | C192: 17400401000214 | D192: 3-Position Terminal Block | E192: 3 | F192: MDCAS2503120010 | G192: VIC-Mel
A193: MBT_18_12_24 | C193: 17400401001516 | D193: Terminal Block | E193: 3 | F193: MDCAS2503120010 | G193: VIC-Mel
A194: MBT_18_12_24 | C194: 17317100A35292 | D194: Wired controller | E194: 8 | F194: MDCAS2503120010 | G194: VIC-Mel
A195: MBT_18_12_24 | C195: 11201007002463 | D195: Discharge Temperature Sensor | E195: 10 | F195: MDCAS2503120010 | G195: VIC-Mel
... A216: MBT_18_12_24 | C216: 11201007000025 | D216: Room Temperature Sensor | E216: 1 | F216: MDCAS2503120010 | G216: VIC-Mel
A217: MBT_18_12_24 | C217: 12200101000533 | D217: Fan Assembly | E217: 11 | F217: MDCAS2503120010 | G217: VIC-Mel
A218: MBT_18_12_24 | C218: 11002015018873 | D218: Brushless DC Motor | E218: 11 | F218: MDCAS2503120010 | G218: VIC-Mel
A219: MBT_18_12_24 | C219: 15500213001346 | D219: Electronic Expansion Valve | E219: 7 | F219: MDCAS2503120010 | G219: VIC-Mel
A220: MBT_18_12_24 | C220: 11201007003438 | D220: Room Temperature Sensor | E220: 7 | F220: MDCAS2503120010 | G220: VIC-Mel
A221: MBT_18_12_24 | C221: 11201007000164 | D221: Pipe Temperature Sensor | E221: 7 | F221: MDCAS2503120010 | G221: VIC-Mel
A222: MBT_18_12_24 | C222: 11201007005723 | D222: Pipe Temperature Sensor | E222: 7 | F222: MDCAS2503120010 | G222: VIC-Mel
A223: MBT_18_12_24 | C223: 11201007005724 | D223: Pipe Temperature Sensor | E223: 7 | F223: MDCAS2503120010 | G223: VIC-Mel
A224: MBT_18_12_24 | C224: 17122300007693 | D224: Indoor Unit Main Control Board | E224: 11 | F224: MDCAS2503120010 | G224: VIC-Mel
A225: MBT_18_12_24 | C225: 17122300007694 | D225: Fan Inverter Module Assembly | E225: 7 | F225: MDCAS2503120010 | G225: VIC-Mel
...

Sheet 物料
A1: Ctn No. | B1: Description | C1: QTY | D1: INV. NO | E1: Destination | F1: Department | G1: ETA | H1: Remark
A2: TCKU7956323 | B2: 冰箱样品 | C2: 1 | D2: - | E2: VIC-Mel | F2: Sales | G2: 45617 | H2: NCE公司
A3: TSSU5063562 | B3: MFAG35VA-N Indoor unit | C3: 2 | D3: MDAJB241107D0005 | E3: VIC-Mel | F3: Marketing | G3: 45630 | H3: RAC道具
B4: MFAG35VA-X3 Outdoor unit | C4: 4 | D4: MDAJB241107D0005 | E4: VIC-Mel | F4: Marketing
B5: Promotional material 无 屏幕演示道具 无 | C5: 3 | D5: MDAJB241107D0005 | E5: VIC-Mel | F5: Marketing
B6: Promotional material 无 石墨烯中型道具 无 | C6: 3 | D6: MDAJB241107D0005 | E6: VIC-Mel | F6: Marketing
B7: Promotional material 无 AEP-2400H 无 | C7: 1 | D7: MDAJB241107D0005 | E7: VIC-Mel | F7: Marketing | H7: RAC展架
B8: Promotional material 无 AEP-2400H 无 | C8: 1 | D8: MDAJB241107D0005 | E8: VIC-Mel | F8: Marketing
B9: Promotional material 无 WG+分体+风管-2400H（大） 无 | C9: 1 | D9: MDAJB241107D0005 | E9: VIC-Mel | F9: Marketing
B10: Promotional material 无 WG+分体+风管-2400H（大） 无 | C10: 1 | D10: MDAJB241107D0005 | E10: VIC-Mel | F10: Marketing
B11: Promotional material 无 WG+分体+风管-2400H（大） 无 | C11: 1 | D11: MDAJB241107D0005 | E11: VIC-Mel | F11: Marketing
B12: Promotional material 无 WG+分体+风管-2400H（大） 无 | C12: 1 | D12: MDAJB241107D0005 | E12: VIC-Mel | F12: Marketing
B13: Promotional material 无 WG+分体+风管-2400H（大） 无 | C13: 1 | D13: MDAJB241107D0005 | E13: VIC-Mel | F13: Marketing
B14: Promotional material 无 WG+分体+风管-2400H（小） 无 | C14: 1 | D14: MDAJB241107D0005 | E14: VIC-Mel | F14: Marketing
B15: Promotional material 无 WG+分体+风管-2400H（小） 无 | C15: 1 | D15: MDAJB241107D0005 | E15: VIC-Mel | F15: Marketing
B16: Promotional material 无 WG+分体+风管-2400H（小） 无 | C16: 1 | D16: MDAJB241107D0005 | E16: VIC-Mel | F16: Marketing
B17: Promotional material 无 WG+分体+风管-2400H（小） 无 | C17: 1 | D17: MDAJB241107D0005 | E17: VIC-Mel | F17: Marketing
B18: Promotional material 无 WG+分体+风管-2400H（小） 无 | C18: 1 | D18: MDAJB241107D0005 | E18: VIC-Mel | F18: Marketing
B19: Promotional material 无 XtremeSave-2400H 无 | C19: 1 | D19: MDAJB241107D0005 | E19: VIC-Mel | F19: Marketing
... B26: 工具包 | C26: 48 | D26: MDAJB241107D0005 | E26: VIC-Mel | F26: Aftersales
B27: MFAB70NB 纸箱 | C27: 1 | D27: - | E27: VIC-Mel | F27: Warehouse | H27: 补柜号：BHCU5008651里面，MFAB70NB的纸箱
B28: Nick 名片 | C28: 1 | D28: - | E28: VIC-Mel | F28: Aftersales | H28: 放在其中一箱工具包里，外箱有写：Nick名片
A29: BSIU9814155 | B29: SDA-MEC60咖箱 | C29: 10 | D29: MDAJB241126D0010 | E29: VIC-Mel | F29: Warehouse | G29: 45648 | H29: FOC
A30: TXGU6734231 | B30: 工具包 | C30: 22 | D30: - | E30: QLD-Brisbane | F30: Aftersales | G30: 45678
A31: TSSU5116615 | B31: RAC简易展架 -美的牌 | C31: 30 | D31: MDAJB250117D0014 | E31: VIC-Mel | F31: Marketing | G31: 45708 | H31: RAC 展架，6.3CBM
B32: MBT行李箱 | C32: 10 | D32: MDAJB250117D0014 | E32: VIC-Mel | F32: Marketing | H32: MBT10个行李箱
B33: 卡片（道歉卡） | C33: 2000 | D33: - | E33: VIC-Mel | F33: Aftersales | H33: 采购物料
B34: 卡片（感谢卡） | C34: 100 | D34: - | E34: VIC-Mel | F34: Aftersales | H34: 采购物料
B35: 水平卷尺 | C35: 1500 | D35: - | E35: VIC-Mel | F35: Aftersales | H35: 采购物料
B36: 纸箱 大盒 42 x 27 x 21cm 中盒 35 x 24 x 20cm 小盒 23 x15 x 5cm | C36: 3000 | D36: - | E36: VIC-Mel | F36: Aftersales | H36: 采购物料
B37: 纸箱（61x61x10cm） | C37: 100 | D37: - | E37: VIC-Mel | F37: Aftersales | H37: 采购物料
B38: 纸箱（90x18x18cm） | C38: 100 | D38: - | E38: VIC-Mel | F38: Aftersales | H38: 采购物料
B39: 笔 | C39: =2010-100 -> 1910 | D39: - | E39: VIC-Mel | F39: Marketing | H39: 采购物料
B40: 地毯 | C40: 100 | D40: - | E40: VIC-Mel | F40: Marketing | H40: 采购物料
B41: 鼠标垫 | C41: 920 | D41: - | E41: VIC-Mel | F41: Marketing | H41: 采购物料
B42: 背包 | C42: 99 | D42: - | E42: VIC-Mel | F42: Marketing | H42: 采购物料
B43: 雨伞 | C43: =800-120 -> 680 | D43: - | E43: VIC-Mel | F43: Marketing | H43: 采购物料
B44: 多功能钥匙工具 | C44: 1500 | D44: - | E44: VIC-Mel | F44: Marketing | H44: 采购物料
B45: 帆布袋 | C45: 875 | D45: - | E45: VIC-Mel | F45: Marketing | H45: 采购物料
B46: 礼品袋 | C46: 500 | D46: - | E46: VIC-Mel | F46: Marketing | H46: 采购物料
B47: 马克杯 | C47: 100 | D47: MDAJB250117D0014 | E47: VIC-Mel | F47: Marketing | H47: 采购物料
B48: 建材资料架 | C48: 10 | D48: - | E48: VIC-Mel | F48: Marketing | H48: 采购物料
B49: 袜子 | C49: 500 | D49: - | E49: VIC-Mel | F49: Marketing | H49: 采购物料
B50: 笔记本 | C50: =500-50 -> 450 | D50: - | E50: VIC-Mel | F50: Marketing | H50: 采购物料
B51: 保温杯 | C51: =100-8 -> 92 | D51: - | E51: VIC-Mel | F51: Marketing | H51: 采购物料
B52: 奖杯 | C52: 11 | D52: - | E52: VIC-Mel | F52: Marketing | H52: 采购物料
B53: 桌布 | C53: 10 | D53: - | E53: VIC-Mel | F53: Marketing | H53: 采购物料，5张旧尺寸：150*200cm。5张新尺寸：180*200cm
B54: 刀旗 | C54: 60 | D54: - | E54: VIC-Mel | F54: Marketing | H54: 采购物料
B55: 指示牌 | C55: 1 | D55: - | E55: VIC-Mel | F55: Marketing | H55: 采购物料
B56: 名牌板 | C56: 1 | D56: - | E56: VIC-Mel | F56: Marketing | H56: 采购物料
B57: MBT易拉宝 | C57: 10 | D57: - | E57: VIC-Mel | F57: Marketing | H57: 采购物料
B58: 杯套 | C58: 2000 | D58: - | E58: VIC-Mel | F58: Marketing | H58: 采购物料
B59: Tradebook | C59: 1912 | D59: - | E59: VIC-Mel | F59: Marketing | H59: 采购物料
B60: Multi Brochure | C60: 2030 | D60: - | E60: VIC-Mel | F60: Marketing | H60: 采购物料
B61: 缠绕膜（手打） | C61: 1350 | D61: - | E61: VIC-Mel | F61: Logistics | H61: 采购物料
B62: 拉膜器 | C62: 150 | D62: - | E62: VIC-Mel | F62: Logistics | H62: 采购物料
B63: 缠绕膜（机打） | C63: 11 | D63: - | E63: VIC-Mel | F63: Logistics | H63: 采购物料
... B71: RAC 17kW分离式风管内机样机 | C71: 1 | D71: MDAJB250117D0013 | E71: VIC-Mel | F71: Justin | H71: FOC
B72: RAC 17kW分离式风管外机样机 | C72: 1 | D72: MDAJB250117D0013 | E72: VIC-Mel | H72: FOC
A73: CSLU6027568 | B73: MDV-V200WN1(AU) | C73: 1 | D73: MDCAS2502210019 | E73: VIC-Mel | F73: Aftersales | G73: 45728 | H73: MBT quality claim-8月VRF +MBT quality claim SP
B74: MIH28GHN18 | C74: 1 | D74: MDCAS2502210019 | E74: VIC-Mel | F74: Aftersales | H74: 2410027V MBT quality claim-10月VRF
B75: MIH28GHN18 | C75: 1 | D75: MDCAS2502210019 | E75: VIC-Mel | F75: Aftersales | H75: 2410075V MBT quality claim-10月VRF
B76: MIH80GHN18 | C76: 1 | D76: MDCAS2502210019 | E76: VIC-Mel | F76: Aftersales | H76: 2410130V MBT quality claim-10月VRF
A77: JXLU6390272 | B77: 铝棒 | C77: 1 | D77: - | E77: VIC-Mel | F77: Justin | G77: 45765
B78: MIH28GHN18-A | C78: 5 | D78: MDCAS2503120010 | E78: VIC-Mel | F78: Justin | H78: 特殊处理的VEU内机，不带电子膨胀阀，入售后部门，不销售（试用样机，FOC）
B79: MIH36GHN18-A | C79: 5 | D79: MDCAS2503120010 | E79: VIC-Mel | F79: Justin | H79: 特殊处理的VEU内机，不带电子膨胀阀，入售后部门，不销售（试用样机，FOC）
B80: MIH80GHN18-A | C80: 5 | D80: MDCAS2503120010 | E80: VIC-Mel | F80: Justin | H80: 特殊处理的VEU内机，不带电子膨胀阀，入售后部门，不销售（试用样机，FOC）
B81: MIH71GHN18-A | C81: 5 | D81: MDCAS2503120010 | E81: VIC-Mel | F81: Justin | H81: 特殊处理的VEU内机，不带电子膨胀阀，入售后部门，不销售（试用样机，FOC）
B82: MDV-V235WN1(AU)-A | C82: 2 | D82: MDCAS2503120010 | E82: VIC-Mel | F82: Justin | H82: MBT quality claim
A83: CSNU8029551 | B83: RAC简易展架-comfee牌 | C83: 5 | D83: MDAJB250331D0010 | E83: WA-Frementle | F83: Fourways | G83: 45770 | H83: 已完货，5.45cbm
A84: By Air: UPS 1ZG074H80437830567 | B84: 热水机五金配件 | C84: 3 | D84: - | E84: VIC-Mel | F84: Justin | G84: 45783 | H84: 含3个三通阀，6支直管等
A85: CAAU8806033 | B85: RAC简易展架 -美的牌 | C85: 3 | D85: MDAJB250406D0003 | E85: NSW-Sydney | F85: Marketing | G85: ='Customs Decl. & Local Delivery'!J593 -> 45773 | H85: 已完货，0.63cbm
A86: TXGU8125620 | B86: 会议室椅子 | C86: 20 | D86: - | E86: VIC-Mel | F86: Admin | G86: 45778
B87: Justin办公室椅子 | C87: 3 | D87: - | E87: VIC-Mel | F87: Justin
A88: GAOU7074979 | B88: MDV-V200WN1(AU) | C88: 3 | D88: MDCAS2504140011 | E88: VIC-Mel | F88: Aftersales | G88: 45787 | H88: MBT quality claim-7月2407081V+2407046V+2407105V
A89: CAAU8805839 | B89: MDV-V200WN1(AU) | C89: 2 | D89: MDCAS2504010030 | E89: VIC-Mel | F89: Aftersales | G89: 45783 | H89: MBT quality claim-7月2407051V+2407090V
A90: TSSU5047556 | B90: 路沿坡 | C90: 8 | D90: MDCAS2504300034 | E90: VIC-Mel | F90: Logistics | G90: 45803 | H90: 已完货，0.075cbm
B91: 扫地机 | C91: 2 | E91: VIC-Mel | F91: Logistics | H91: 0.7cbm
B92: 卷膜sample | C92: 1 | E92: VIC-Mel | F92: Logistics
B93: MBT 双肩包 | C93: 20 | E93: VIC-Mel | F93: Marketing
B94: MIH36GHN18 | C94: 2 | E94: VIC-Mel | F94: Aftersales | H94: MBT Quality Claim for Jan,2025.2411001V
B95: MIH56GHN18 | C95: 2 | E95: VIC-Mel | F95: Aftersales | H95: MBT Quality Claim for Jan,2025.2412117V & 2502186V
B96: MIH28GHN18 | C96: 1 | E96: VIC-Mel | F96: Aftersales | H96: MBT Quality Claim for Feb,2025.2501139V
A97: - | B97: MBT遥控支架 | C97: 250 | D97: - | E97: VIC-Mel | G97: 45800 | H97: 空运DHL_3010754832，FOC
A98: - | B98: 标签机 | C98: 1 | D98: - | E98: VIC-Mel | F98: Logistics | G98: 45811 | H98: 含电池，RAC Henry 6.3带到澳洲
B99: PDA手柄 | C99: 2 | D99: - | E99: VIC-Mel | F99: Logistics | H99: RAC Henry 6.3带到澳洲
B100: PDA | C100: 1 | D100: - | E100: VIC-Mel | F100: Logistics | H100: 含电池，RAC Henry 6.3带到澳洲
A101: FFAU3102544 | B101: RAC 235热水机样机：MHP235I-E1 | C101: 2 | D101: MDAWSJHN250513A | E101: VIC-Mel | F101: Justin | G101: 45811 | H101: FOC，已贴A4纸标注样机贴在纸箱上
A102: - | B102: PDA | C102: 9 | D102: - | E102: VIC-Mel | F102: Logistics | G102: 45816 | H102: 含电池，已交付给澳洲同事
A103: - | B103: 标签机 | C103: 3 | D103: - | E103: VIC-Mel | F103: Logistics | G103: 45816 | H103: 含电池，已交付给澳洲同事
A104: By Air：DHL 8114010752 | B104: 6星EZ 2.6kW | C104: 1 | D104: BOJ2535246L1 | E104: VIC-Mel | F104: 光哥 | G104: 45824 | H104: RAC 新品内机,收到机器后麻烦对接光哥和梦诗姐查看
B105: 5星EF 2.6kW | C105: 1 | E105: VIC-Mel | F105: 光哥 | G105: 45824
B106: 5星EF 3.5kW | C106: 1 | E106: VIC-Mel | F106: 光哥 | G106: 45824
A107: TXGU5778554 | B107: DUCMI125IHC | C107: 1 | D107: MDAJSJHN250526A | E107: VIC-Mel | F107: Justin | G107: 45826 | H107: RAC风管机样机 FOC
B108: UCMI125OC | C108: 1 | D108: MDAJSJHN250526A | E108: VIC-Mel | F108: Justin
B109: DUCMI170IHC | C109: 1 | D109: MDAJSJHN250526A | E109: VIC-Mel | F109: Justin
B110: UCMI170OC | C110: 1 | D110: MDAJSJHN250526A | E110: VIC-Mel | F110: Justin
A111: DFSU7784910 | B111: RAC简易展架 -美的牌 | C111: 7 | D111: MDAJB250524D0010 | E111: QLD-Brisbane | F111: Marketing | G111: 45837 | H111: 已完货，1.47cbm
A112: SNBU8367624 | B112: RAC简易展架-comfee牌 | C112: 5 | D112: MDAJB250526D0008 | E112: QLD-Brisbane | F112: Fourways | G112: 45837 | H112: 已完货，5.45cbm
A113: FFAU3196203 | B113: RAC 235热水机样机：MHP235I-E1 | C113: 1 | D113: MDAWSJHN250529A | E113: VIC-Mel | F113: Justin | G113: 45850 | H113: FOC
...
